<?xml version="1.0" encoding="UTF-8" standalone="yes" ?>
<Config XXName="【日文】文字描述ID配置表">
  <Text Type="1" TypeTxt="通用">
    <List Id="1" Txt="OK" />
    <List Id="2" Txt="キャンセル" />
    <List Id="3" Txt="プレイヤー" />
    <List Id="4" Txt="送信" />
    <List Id="5" Txt="%d 宝石を購入しました！" />
    <List Id="6" Txt="魔法はいっぱいです！" />
    <List Id="7" Txt="本当に退出しますか？" />
    <List Id="8" Txt="経験値：" />
    <List Id="9" Txt="アップデート" />
    <List Id="10" Txt="バージョン" />
    <List Id="11" Txt="Copyright 2012-2013 IGG.COM All Rights Reserved" />
    <List Id="12" Txt="Help.castle.jp@igg.com" />
    <List Id="13" Txt="自分" />
    <List Id="14" Txt="ボーナス！" />
    <List Id="15" Txt="売却" />
    <List Id="16" Txt="バトル" />
    <List Id="17" Txt="しばらく中断されていました。ゲームに戻るにはリロードをタップしてください。" />
    <List Id="18" Txt="まだプレイしていますか？" />
    <List Id="19" Txt="リロード" />
    <List Id="20" Txt="スキップ" />
    <List Id="21" Txt="開始" />
    <List Id="22" Txt="ロード中" />
    <List Id="23" Txt="栄光ポイント" />
    <List Id="24" Txt="NONE" />
    <List Id="51" Txt="情報" />
    <List Id="52" Txt="レベルアップ" />
    <List Id="53" Txt="雇用" />
    <List Id="54" Txt="収集" />
    <List Id="55" Txt="ヒーロー" />
    <List Id="56" Txt="削除" />
    <List Id="57" Txt="魔法" />
    <List Id="58" Txt="訓練" />
    <List Id="59" Txt="参加" />
    <List Id="60" Txt="ヒーローの変更" />
    <List Id="61" Txt="%s (レベル %d)" />
    <List Id="62" Txt="全列" />
    <List Id="63" Txt="完了" />
    <List Id="64" Txt="%s レベル %d -> %d" />
    <List Id="65" Txt="接続に失敗" />
    <List Id="66" Txt="再接続" />
    <List Id="67" Txt="終了" />
    <List Id="68" Txt="注意" />
    <List Id="69" Txt="宝石が足りません！今すぐ購入しますか？" />
    <List Id="70" Txt="名前の入力" />
    <List Id="71" Txt="この名前はすでに使用されているもしくは使用不可な文字が含まれています！違う名前を選んでください。" />
    <List Id="72" Txt="回転" />
    <List Id="73" Txt="全レベル" />
    <List Id="74" Txt="レベル %d" />
    <List Id="75" Txt="アカウントが正しく認識されません。詳しくはライブサポートまでご連絡ください。" />
    <List Id="76" Txt="あなたのターゲットはオンラインです。戦闘中止となります。" />
    <List Id="77" Txt="円" />
    <List Id="78" Txt="世界" />
    <List Id="99" Txt="使用する" />
    <List Id="100" Txt="推進する" />
    <List Id="101" Txt="部隊は攻撃だけでなく、防御においても重要です。" />
    <List Id="102" Txt="バトルで勝利を収めた部隊が基地に戻ります。" />
    <List Id="103" Txt="部隊を配置するには、攻撃時に画面をタップしてください。または画面上で長押しすることで、急速に部隊を連続配置することができます。" />
    <List Id="104" Txt="赤く網掛けされたエリアには部隊を配置できません。" />
    <List Id="105" Txt="部隊の雇用は軍隊キャンプで行えます。部隊は自らの軍隊キャンプ周辺を防御します。" />
    <List Id="106" Txt="軍隊キャンプをアップグレードすることで、収容能力や雇用列、および部隊のパトロール範囲の拡大が行えます。" />
    <List Id="107" Txt="ダンジョンをクリアすることでたくさんの資源を勝ち取り、戦力を証明しましょう！" />
    <List Id="108" Txt="ダンジョンでヒーローの欠片を集めて、強いヒーローたちと交換しましょう！" />
    <List Id="109" Txt="構造物の建設やアップグレード、町の拡大、そして町の防御を向上させて、難攻不落の要塞を作り上げてください！" />
    <List Id="110" Txt="適切な建物の配置と用意が最も効果的な防衛戦略になります。" />
    <List Id="111" Txt="初心者用ガイド" />
    <List Id="112" Txt="[町の館]をアップグレードして、建物のアンロック・レベルアップ・数の増加" />
    <List Id="113" Txt="[町の館]のアップグレードが最も重要のことです！" />
    <List Id="114" Txt="建物を選択して空のスロットへ移動してください。建物を重ねて配置することはできません。" />
    <List Id="115" Txt="配置できる新しい建物がある時は、ショップボタンに数字アイコンが表示されます。" />
    <List Id="116" Txt="とても重要な資源のひとつ、名誉の印です。
これを使用してヒーロー雇用が行え、スターレベルが上昇できます。
主に闘技場内で獲得できますが、急襲やダンジョンにおいても獲得可能です。" />
    <List Id="117" Txt="これがあなたのマイトです。総合能力を表しています。
建物をアップグレードして部隊とヒーローを訓練することでマイトが強くなります。
相手を選択する時にマイトが指標であります。" />
    <List Id="201" Txt="ヒーローがバトル中で一番役立っていて、もちろん継続訓練が必要です。" />
    <List Id="202" Txt="部隊をアップグレードすることで、彼らを強くするだけでなく別の種類の部隊もアンロックできます。" />
    <List Id="203" Txt="異なる部隊同士の抑制関係に注意してください。戦闘時に役に立つでしょう。" />
    <List Id="204" Txt="ヒーローを戦闘に使用することと、レベルアップへつながります。" />
    <List Id="205" Txt="闘技場ランクが高いほど、より多くの栄光ポイントを獲得できます。" />
    <List Id="206" Txt="魔法を適切に使用すると戦局を転換させるかもしれません。" />
    <List Id="207" Txt="オフラインでも盾を購入すれば城を襲われないように続けて守ってくれます。" />
    <List Id="208" Txt="ダンジョンは資源の宝庫というだけでなく、部隊の訓練にも最適です。" />
    <List Id="209" Txt="アップグレードされた基本の塔には多大な防御能力があり、高級な塔へ変化させることもできます！" />
    <List Id="210" Txt="敵の攻撃を弱めるために、建物の配置は入念に！" />
    <List Id="211" Txt="ヒーローの祭壇でレアなヒーローたちを雇用しましょう！" />
    <List Id="212" Txt="戦闘でスライムを使用することはできません。その代わり、ヒーローのスキルレベルの増加に使用できます。" />
    <List Id="213" Txt="欠片・宝石・名誉を使用することで、ヒーローを雇用できます。" />
    <List Id="500" Txt="デバイス情報をロード中…" />
    <List Id="501" Txt="デバイス情報をロードできませんでした！" />
    <List Id="502" Txt="デバイス情報のロード完了！" />
    <List Id="510" Txt="サーバー情報ロード中..." />
    <List Id="511" Txt="サーバー情報をロードできませんでした！" />
    <List Id="512" Txt="サーバー情報のロード完了！" />
    <List Id="520" Txt="アカウント情報をロード中…" />
    <List Id="521" Txt="アカウント情報をロードできませんでした！" />
    <List Id="522" Txt="アカウント情報のロード完了！" />
    <List Id="530" Txt="サーバーに接続中…" />
    <List Id="531" Txt="ログインサーバーへ接続できませんでした！" />
    <List Id="532" Txt="ログインサーバーへの接続完了！" />
    <List Id="540" Txt="サーバーへ接続中…" />
    <List Id="541" Txt="ゲームサーバーへ接続できませんでした！" />
    <List Id="542" Txt="ゲームサーバーへの接続完了！" />
    <List Id="550" Txt="ネットワークエラーです！" />
    <List Id="551" Txt="接続に失敗しました！ネットワーク状況をご確認の上、再試行してください。" />
    <List Id="552" Txt="名前に使用できるのは、英数字のみです。" />
    <List Id="553" Txt="名前が長すぎます！" />
    <List Id="554" Txt="サーバーエラー：%d" />
    <List Id="1001" Txt="HP：" />
    <List Id="1002" Txt="生産：" />
    <List Id="1003" Txt="貯蔵：" />
    <List Id="1004" Txt="アップグレード時間" />
    <List Id="1005" Txt="必要な資源" />
    <List Id="1006" Txt="攻撃" />
    <List Id="1007" Txt="ダメージ：" />
    <List Id="1008" Txt="警戒範囲：" />
    <List Id="1101" Txt="収容量" />
    <List Id="1102" Txt="合計時間" />
    <List Id="1103" Txt="必要なスペース" />
    <List Id="1104" Txt="生産コスト" />
    <List Id="1105" Txt="今すぐ終了" />
    <List Id="1106" Txt="スペース：" />
    <List Id="1120" Txt="ヒーローを配置するにはそのアイコンをタップしてください。" />
    <List Id="1201" Txt="ランキング" />
    <List Id="1202" Txt="ランク" />
    <List Id="1203" Txt="名前:" />
    <List Id="1204" Txt="マイト:" />
    <List Id="1205" Txt="オプション" />
    <List Id="1206" Txt="確認" />
    <List Id="1207" Txt="攻撃" />
    <List Id="1301" Txt="火砲の変更を表示します。切り替えるにはタップしてください。" />
    <List Id="1302" Txt="アップグレード" />
    <List Id="1401" Txt="完了" />
    <List Id="1402" Txt="報酬:" />
    <List Id="1501" Txt="バトルの開始" />
    <List Id="1502" Txt="残り時間" />
    <List Id="1503" Txt="戦利品" />
    <List Id="1504" Txt="バトルの終了" />
    <List Id="1505" Txt="敗北数" />
    <List Id="1506" Txt="敵の敗北数" />
    <List Id="1507" Txt="次へ" />
    <List Id="1508" Txt="ゴールドが足りません。" />
    <List Id="1509" Txt="部隊不足のため、攻撃を開始できません。" />
    <List Id="1510" Txt="作動中の盾でターゲットを攻撃することはできません。" />
    <List Id="1511" Txt="オンライン中のターゲットを攻撃することはできません。" />
    <List Id="1512" Txt="バトルの結果" />
    <List Id="1513" Txt="%s 前" />
    <List Id="1514" Txt="戦闘中のターゲットを攻撃することはできません。" />
    <List Id="1515" Txt="勝利" />
    <List Id="1516" Txt="敗北" />
    <List Id="1517" Txt="獲得：" />
    <List Id="1518" Txt="損失：" />
    <List Id="1519" Txt="別のプレイヤーを攻撃すると、盾が無効化されます。本当に攻撃しますか？" />
    <List Id="1601" Txt="宝物" />
    <List Id="1602" Txt="盾" />
    <List Id="1603" Txt="装飾品" />
    <List Id="1604" Txt="資源" />
    <List Id="1605" Txt="軍隊" />
    <List Id="1606" Txt="防御" />
    <List Id="1607" Txt="ショップ" />
    <List Id="1608" Txt="必要レベル %d %s" />
    <List Id="1609" Txt="アンロックするには %d レベル %s が必要です。" />
    <List Id="1611" Txt="宝石の購入" />
    <List Id="1612" Txt="ゴールドの購入" />
    <List Id="1613" Txt="マナの購入" />
    <List Id="1614" Txt="240 宝石" />
    <List Id="1615" Txt="600 宝石" />
    <List Id="1616" Txt="1,200 宝石" />
    <List Id="1617" Txt="10% ゴールドを購入する" />
    <List Id="1618" Txt="50% ゴールドを購入する" />
    <List Id="1619" Txt="ゴールド貯蔵庫をいっぱいにする" />
    <List Id="1620" Txt="10% マナを購入する" />
    <List Id="1621" Txt="50% マナを購入する" />
    <List Id="1622" Txt="マナ貯蔵庫をいっぱいにする" />
    <List Id="1623" Txt="盾を有効化する" />
    <List Id="1624" Txt="%d 時間" />
    <List Id="1625" Txt="%d ゴールド" />
    <List Id="1626" Txt="%d マナ" />
    <List Id="1627" Txt="購入不可能" />
    <List Id="1628" Txt="これにはもっとゴールドが必要です。" />
    <List Id="1629" Txt="これにはもっとマナが必要です。" />
    <List Id="1630" Txt="これにはもっと宝石が必要です。" />
    <List Id="1631" Txt="%d ゴールドを購入しますか？" />
    <List Id="1632" Txt="%d マナを購入しますか？" />
    <List Id="1633" Txt="もっと宝石を購入しますか？" />
    <List Id="1634" Txt="ゴールドの購入" />
    <List Id="1635" Txt="マナの購入" />
    <List Id="1636" Txt="建設員たちは仕事中です！" />
    <List Id="1637" Txt="別の工事を完了させて、建設員を利用可能にしますか？" />
    <List Id="1638" Txt="スピードアップ" />
    <List Id="1639" Txt="今すぐ完了させますか？" />
    <List Id="1640" Txt="%s を購入しますか？" />
    <List Id="1641" Txt="%s %s を購入しますか？" />
    <List Id="1642" Txt="マナ" />
    <List Id="1643" Txt="ゴールド" />
    <List Id="1644" Txt="盾の持続時間" />
    <List Id="1651" Txt="さらに建物を追加するには、町の館をアップグレードしてください。　" />
    <List Id="1652" Txt="建物数が上限に到達" />
    <List Id="1653" Txt="建設員の追加" />
    <List Id="1654" Txt="建設員を追加しますか？" />
    <List Id="1655" Txt="工事をスピードアップするために、%d ゴールドを購入しますか？" />
    <List Id="1656" Txt="工事をスピードアップするために、%d マナを購入しますか？" />
    <List Id="1657" Txt="このアップグレードをキャンセルすると、資源は50%しか戻ってきません。本当にキャンセルしますか？" />
    <List Id="1658" Txt="レベルアップするために、%d ゴールドを使用しますか？" />
    <List Id="1659" Txt="2,400 宝石" />
    <List Id="1660" Txt="6,000 宝石" />
    <List Id="1661" Txt="12,000 宝石" />
    <List Id="1671" Txt="木の盾" />
    <List Id="1672" Txt="鉄の盾" />
    <List Id="1673" Txt="金の盾" />
    <List Id="1674" Txt="これには %d 宝石が必要です。よろしいですか？" />
    <List Id="1701" Txt="設定" />
    <List Id="1702" Txt="音楽" />
    <List Id="1703" Txt="音響" />
    <List Id="1704" Txt="言語" />
    <List Id="1705" Txt="詳細" />
    <List Id="1706" Txt="ヘルプ" />
    <List Id="1707" Txt="閉じる" />
    <List Id="1801" Txt="使用するヒーローを選択してください。" />
    <List Id="1802" Txt="選択してください" />
    <List Id="1803" Txt="雇用" />
    <List Id="1804" Txt="レベル" />
    <List Id="1805" Txt="アップグレード" />
    <List Id="1806" Txt="アップグレード条件" />
    <List Id="1807" Txt="クリアする" />
    <List Id="1808" Txt="使用する" />
    <List Id="1809" Txt="1回引く" />
    <List Id="1810" Txt="5回引く" />
    <List Id="1811" Txt="栄光ポイントで雇用" />
    <List Id="1812" Txt="宝石で雇用" />
    <List Id="1813" Txt="栄光ポイントを使用してヒーローを雇用してください。" />
    <List Id="1814" Txt="クーポンを使用してヒーローを雇用してください。レアなヒーローを獲得できるかも！" />
    <List Id="1815" Txt="おめでとうございます！" />
    <List Id="1816" Txt="ヒーローショップ" />
    <List Id="1817" Txt="欠片で雇用" />
    <List Id="1818" Txt="経験値アップ" />
    <List Id="1819" Txt="スター" />
    <List Id="1820" Txt="ヒーローを復活しますか？" />
    <List Id="1821" Txt="ハイレベルやハイスキルのヒーローも含めていますがこのままよろしいですか？
" />
  </Text>
  <Text Type="2" TypeTxt="建筑名称">
    <List Id="10001" Txt="町の館" />
    <List Id="10002" Txt="ヒーローの祭壇" />
    <List Id="10003" Txt="軍隊キャンプ" />
    <List Id="10004" Txt="ゴールド採鉱場" />
    <List Id="10005" Txt="マナ工場" />
    <List Id="10006" Txt="ゴールド貯蔵庫" />
    <List Id="10007" Txt="マナ貯蔵庫" />
    <List Id="10008" Txt="監視塔" />
    <List Id="10009" Txt="矢の塔" />
    <List Id="10010" Txt="魔法の塔" />
    <List Id="10011" Txt="闘技場" />
    <List Id="10012" Txt="魔法の館" />
    <List Id="10013" Txt="城壁" />
    <List Id="10014" Txt="偽装爆弾" />
    <List Id="10015" Txt="ヒーロー基地" />
    <List Id="10016" Txt="訓練場" />
    <List Id="10017" Txt="墓碑" />
    <List Id="10018" Txt="火砲塔" />
    <List Id="10019" Txt="栄光の館" />
    <List Id="10021" Txt="ヒーロートラップ" />
    <List Id="10101" Txt="花 I" />
    <List Id="10102" Txt="花 II" />
    <List Id="10103" Txt="花 III" />
    <List Id="10104" Txt="花 IV" />
    <List Id="10105" Txt="花 V" />
    <List Id="10111" Txt="彫像 I" />
    <List Id="10112" Txt="彫像 II" />
    <List Id="10113" Txt="彫像 III" />
    <List Id="10114" Txt="彫像 IV" />
    <List Id="10115" Txt="彫像 V" />
    <List Id="10121" Txt="その他 I" />
    <List Id="10122" Txt="その他 II" />
    <List Id="10123" Txt="その他 III" />
    <List Id="10124" Txt="その他 IV" />
    <List Id="10125" Txt="その他 V" />
    <List Id="10131" Txt="草 I" />
    <List Id="10132" Txt="草 II" />
    <List Id="10133" Txt="草 III" />
    <List Id="10134" Txt="草 IV" />
    <List Id="10135" Txt="草 V" />
    <List Id="10141" Txt="石 I" />
    <List Id="10142" Txt="石 II" />
    <List Id="10143" Txt="石 III" />
    <List Id="10144" Txt="石 IV" />
    <List Id="10145" Txt="石 V" />
    <List Id="10151" Txt="樹 I" />
    <List Id="10152" Txt="樹 II" />
    <List Id="10153" Txt="樹 III" />
    <List Id="10154" Txt="樹 IV" />
    <List Id="10155" Txt="樹 V" />
    <List Id="10201" Txt="A" />
    <List Id="10202" Txt="B" />
    <List Id="10203" Txt="C" />
    <List Id="10204" Txt="D" />
    <List Id="10205" Txt="E" />
    <List Id="10206" Txt="F" />
    <List Id="10207" Txt="G" />
    <List Id="10208" Txt="H" />
    <List Id="10209" Txt="I" />
    <List Id="10210" Txt="J" />
    <List Id="10211" Txt="K" />
    <List Id="10212" Txt="L" />
    <List Id="10213" Txt="M" />
    <List Id="10214" Txt="N" />
    <List Id="10215" Txt="O" />
    <List Id="10216" Txt="P" />
    <List Id="10217" Txt="Q" />
    <List Id="10218" Txt="R" />
    <List Id="10219" Txt="S" />
    <List Id="10220" Txt="T" />
    <List Id="10221" Txt="U" />
    <List Id="10222" Txt="V" />
    <List Id="10223" Txt="W" />
    <List Id="10224" Txt="X" />
    <List Id="10225" Txt="Y" />
    <List Id="10226" Txt="Z" />
    <List Id="10227" Txt="0" />
    <List Id="10228" Txt="1" />
    <List Id="10229" Txt="2" />
    <List Id="10230" Txt="3" />
    <List Id="10231" Txt="4" />
    <List Id="10232" Txt="5" />
    <List Id="10233" Txt="6" />
    <List Id="10234" Txt="7" />
    <List Id="10235" Txt="8" />
    <List Id="10236" Txt="9" />
    <List Id="10301" Txt="文字と数字を使って面白く組み合わせることができます。" />
  </Text>
  <Text Type="3" TypeTxt="建筑描述">
    <List Id="20001" Txt="あなたの主要建物です。このレベルによって、数・種類・他の建物の上限レベルが決定されます。" />
    <List Id="20002" Txt="ここでヒーローの雇用と訓練を行えます。さらなるアップグレードによってヒーローの回復時間が減少されます。" />
    <List Id="20003" Txt="様々な部隊を生産します。レベルアップすることで、部隊の上限数を増加できます。攻撃される時は部隊の配置は自動的に行われます。" />
    <List Id="20004" Txt="ゴールドを生産します。レベルアップすることで、産量と貯蔵スペースを増加できます。" />
    <List Id="20005" Txt="マナを生産します。レベルアップすることで、産量と貯蔵スペースを増加できます。" />
    <List Id="20006" Txt="収集したゴールドを貯蔵します。レベルアップすることで、貯蔵スペースを増加できます。" />
    <List Id="20007" Txt="収集したマナを貯蔵します。レベルアップすることで、貯蔵スペースを増加できます。" />
    <List Id="20008" Txt="基本の防御塔です。敵部隊を攻撃します。レベル10に到達後、高級な塔にアップグレードが可能です。" />
    <List Id="20009" Txt="レベル10に達した塔は、単一ターゲットを迅速に攻撃します。" />
    <List Id="20010" Txt="レベル10に達した塔は、複数ターゲットを一気に攻撃します。" />
    <List Id="20011" Txt="ヒーローは闘技場で栄光ポイントを獲得できます。" />
    <List Id="20012" Txt="各道具を使って攻撃する時思い付かない効果が出ます。" />
    <List Id="20013" Txt="防御の最前線です。敵の侵攻を妨げるために戦略的に配置してください。" />
    <List Id="20014" Txt="敵の兵隊が踏むと爆発させてダメージを与えます、消耗品で、飛行ユニットに効きません。" />
    <List Id="20015" Txt="ヒーローをここに配置して、敵を襲撃させます。また攻撃される時も敵を攻められます。" />
    <List Id="20016" Txt="部隊をアップグレードして、より多種な部隊をアンロックします。" />
    <List Id="20017" Txt="部隊が全滅すると墓碑が表示されます。" />
    <List Id="20018" Txt="高級の塔の砲弾が周辺のターゲットにダメージを与えます。" />
    <List Id="20019" Txt="栄光の館" />
    <List Id="20020" Txt="射程範囲：" />
    <List Id="20021" Txt="ヒーローが近付くと爆発し、有効エリア内にいるヒーローに10％のダメージを与えます。多数配置するともっと効果が出ます。消耗品であり、飛行ユニットには効きません。" />
    <List Id="20101" Txt="装飾用の花" />
    <List Id="20102" Txt="装飾用の花" />
    <List Id="20103" Txt="装飾用の花" />
    <List Id="20104" Txt="装飾用の花" />
    <List Id="20105" Txt="装飾用の花" />
    <List Id="20111" Txt="装飾用の彫像" />
    <List Id="20112" Txt="装飾用の彫像" />
    <List Id="20113" Txt="装飾用の彫像" />
    <List Id="20114" Txt="装飾用の彫像" />
    <List Id="20115" Txt="装飾用の彫像" />
    <List Id="20121" Txt="装飾用のアイテム" />
    <List Id="20122" Txt="装飾用のアイテム" />
    <List Id="20123" Txt="装飾用のアイテム" />
    <List Id="20124" Txt="装飾用のアイテム" />
    <List Id="20125" Txt="装飾用のアイテム" />
    <List Id="20131" Txt="削除できます。" />
    <List Id="20132" Txt="削除できます。" />
    <List Id="20133" Txt="削除できます。" />
    <List Id="20134" Txt="削除できます。" />
    <List Id="20135" Txt="削除できます。" />
    <List Id="20141" Txt="削除できます。" />
    <List Id="20142" Txt="削除できます。" />
    <List Id="20143" Txt="削除できます。" />
    <List Id="20144" Txt="削除できます。" />
    <List Id="20145" Txt="削除できます。" />
    <List Id="20151" Txt="削除できます。" />
    <List Id="20152" Txt="削除できます。" />
    <List Id="20153" Txt="削除できます。" />
    <List Id="20154" Txt="削除できます。" />
    <List Id="20155" Txt="削除できます。" />
  </Text>
  <Text Type="4" TypeTxt="魔法">
    <List Id="30001" Txt="矢の雨" />
    <List Id="30002" Txt="矢の雨" />
    <List Id="30003" Txt="矢の雨" />
    <List Id="30004" Txt="矢の雨" />
    <List Id="30005" Txt="矢の雨" />
    <List Id="30006" Txt="修復" />
    <List Id="30007" Txt="修復" />
    <List Id="30008" Txt="修復" />
    <List Id="30009" Txt="修復" />
    <List Id="30010" Txt="修復" />
    <List Id="30011" Txt="アレスの情熱" />
    <List Id="30012" Txt="アレスの情熱" />
    <List Id="30013" Txt="アレスの情熱" />
    <List Id="30014" Txt="アレスの情熱" />
    <List Id="30015" Txt="アレスの情熱" />
    <List Id="30016" Txt="暴風" />
    <List Id="30017" Txt="暴風" />
    <List Id="30018" Txt="暴風" />
    <List Id="30019" Txt="暴風" />
    <List Id="30020" Txt="暴風" />
    <List Id="30021" Txt="守護天使" />
    <List Id="30022" Txt="守護天使" />
    <List Id="30023" Txt="守護天使" />
    <List Id="30024" Txt="守護天使" />
    <List Id="30025" Txt="守護天使" />
    <List Id="30026" Txt="流星" />
    <List Id="30027" Txt="流星" />
    <List Id="30028" Txt="流星" />
    <List Id="30029" Txt="流星" />
    <List Id="30030" Txt="流星" />
    <List Id="30031" Txt="厄災" />
    <List Id="30032" Txt="厄災" />
    <List Id="30033" Txt="厄災" />
    <List Id="30034" Txt="厄災" />
    <List Id="30035" Txt="厄災" />
    <List Id="30036" Txt="アレスの激高" />
    <List Id="30037" Txt="アレスの激高" />
    <List Id="30038" Txt="アレスの激高" />
    <List Id="30039" Txt="アレスの激高" />
    <List Id="30040" Txt="アレスの激高" />
    <List Id="30041" Txt="フェニックスの飛行" />
    <List Id="30042" Txt="フェニックスの飛行" />
    <List Id="30043" Txt="フェニックスの飛行" />
    <List Id="30044" Txt="フェニックスの飛行" />
    <List Id="30045" Txt="フェニックスの飛行" />
    <List Id="30046" Txt="吹雪" />
    <List Id="30047" Txt="吹雪" />
    <List Id="30048" Txt="吹雪" />
    <List Id="30049" Txt="吹雪" />
    <List Id="30050" Txt="吹雪" />
  </Text>
  <Text Type="5" TypeTxt="魔法描述">
    <List Id="31001" Txt="エリア内に矢を降らせ、8秒間エリア内の全敵部隊に最大 HP の8% + 120 のダメージを与えます。建物への影響はありません。" />
    <List Id="31002" Txt="エリア内に矢を降らせ、8秒間エリア内の全敵部隊に最大 HP の8% + 240 のダメージを与えます。建物への影響はありません。" />
    <List Id="31003" Txt="エリア内に矢を降らせ、8秒間エリア内の全敵部隊に最大 HP の8% + 360 のダメージを与えます。建物への影響はありません。" />
    <List Id="31004" Txt="エリア内に矢を降らせ、8秒間エリア内の全敵部隊に最大 HP の8% + 480 のダメージを与えます。建物への影響はありません。" />
    <List Id="31005" Txt="エリア内に矢を降らせ、8秒間エリア内の全敵部隊に最大 HP の8% + 600 のダメージを与えます。建物への影響はありません。" />
    <List Id="31006" Txt="戦場に回復サークルを配置し、8秒間エリア内の全味方部隊に最大 HP の6% + 10 HP の回復を行います。" />
    <List Id="31007" Txt="戦場に回復サークルを配置し、8秒間エリア内の全味方部隊に最大 HP の8% + 20 HP の回復を行います。" />
    <List Id="31008" Txt="戦場に回復サークルを配置し、8秒間エリア内の全味方部隊に最大 HP の10% + 30 HP の回復を行います。" />
    <List Id="31009" Txt="戦場に回復サークルを配置し、8秒間エリア内の全味方部隊に最大 HP の12% + 40 HP の回復を行います。" />
    <List Id="31010" Txt="戦場に回復サークルを配置し、8秒間エリア内の全味方部隊に最大 HP の15% + 50 HP の回復を行います。" />
    <List Id="31011" Txt="自分の全部隊にアレスのパワーを引き起こし、バトル終了までの間 + 5%の攻撃力を与えます。" />
    <List Id="31012" Txt="自分の全部隊にアレスのパワーを引き起こし、バトル終了までの間 + 8%の攻撃力を与えます。" />
    <List Id="31013" Txt="自分の全部隊にアレスのパワーを引き起こし、バトル終了までの間 + 11%の攻撃力を与えます。" />
    <List Id="31014" Txt="自分の全部隊にアレスのパワーを引き起こし、バトル終了までの間 + 14%の攻撃力を与えます。" />
    <List Id="31015" Txt="自分の全部隊にアレスのパワーを引き起こし、バトル終了までの間 + 17%の攻撃力を与えます。" />
    <List Id="31016" Txt="敵の基地をハリケーンで一掃し、8秒間通過上にある敵の全建物に最大 HP の8% + 800 ダメージを与えます。デバイスを傾けて嵐の方向をコントロールしてください。" />
    <List Id="31017" Txt="敵の基地をハリケーンで一掃し、8秒間通過上にある敵の全建物に最大 HP の16% + 1040 ダメージを与えます。デバイスを傾けて嵐の方向をコントロールしてください。" />
    <List Id="31018" Txt="敵の基地をハリケーンで一掃し、8秒間通過上にある敵の全建物に最大 HP の24% + 1280 ダメージを与えます。デバイスを傾けて嵐の方向をコントロールしてください。" />
    <List Id="31019" Txt="敵の基地をハリケーンで一掃し、8秒間に通過上にある敵の全建物に最大 HP の32% + 1520 ダメージを与えます。デバイスを傾けて嵐の方向をコントロールしてください。" />
    <List Id="31020" Txt="敵の基地をハリケーンで一掃し、8秒間通過上にある敵の全建物に最大 HP の40% + 1760 ダメージを与えます。デバイスを傾けて嵐の方向をコントロールしてください。" />
    <List Id="31021" Txt="天使の護衛を召喚し、6秒間エリア内の味方6部隊を不死身にします。" />
    <List Id="31022" Txt="天使の護衛を召喚し、6秒間エリア内の味方8部隊を不死身にします。" />
    <List Id="31023" Txt="天使の護衛を召喚し、6秒間エリア内の味方10部隊を不死身にします。" />
    <List Id="31024" Txt="天使の護衛を召喚し、6秒間エリア内の味方12部隊を不死身にします。" />
    <List Id="31025" Txt="天使の護衛を召喚し、6秒間エリア内の味方14部隊を不死身にします。" />
    <List Id="31026" Txt="エリア内に星を降らせ、6秒間エリア内の全敵部隊に最大 HP の6%のダメージを与えます。" />
    <List Id="31027" Txt="エリア内に星を降らせ、6秒間エリア内の全敵部隊に最大 HP の12%のダメージを与えます。" />
    <List Id="31028" Txt="エリア内に星を降らせ、6秒間エリア内の全敵部隊に最大 HP の18%のダメージを与えます。" />
    <List Id="31029" Txt="エリア内に星を降らせ、6秒間エリア内の全敵部隊に最大 HP の24%のダメージを与えます。" />
    <List Id="31030" Txt="エリア内に星を降らせ、6秒間エリア内の全敵部隊に最大 HP の30%のダメージを与えます。" />
    <List Id="31031" Txt="戦場内に巨大石を転がし、5秒間通過上にいる全敵部隊に最大 HP の10% + 300 ダメージを与えます。さらに、5秒間影響下にある敵部隊の攻撃力を20%減少させます。デバイスを傾けて巨大石の進行方向をコントロールしてください。" />
    <List Id="31032" Txt="戦場内に巨大石を転がし、5秒間通過上にいる全敵部隊に最大 HP の10% + 450 ダメージを与えます。さらに、5秒間影響下にある敵部隊の攻撃力を25%減少させます。デバイスを傾けて巨大石の進行方向をコントロールしてください。" />
    <List Id="31033" Txt="戦場内に巨大石を転がし、5秒間通過上にいる全敵部隊に最大 HP の10% + 600 ダメージを与えます。さらに、5秒間影響下にある敵部隊の攻撃力を30%減少させます。デバイスを傾けて巨大石の進行方向をコントロールしてください。" />
    <List Id="31034" Txt="戦場内に巨大石を転がし、5秒間通過上にいる全敵部隊に最大 HP の10% + 750 ダメージを与えます。さらに、5秒間影響下にある敵部隊の攻撃力を35%減少させます。デバイスを傾けて巨大石の進行方向をコントロールしてください。" />
    <List Id="31035" Txt="戦場内に巨大石を転がし、5秒間通過上にいる全敵部隊に最大 HP の10% + 900 ダメージを与えます。さらに、5秒間影響下にある敵部隊の攻撃力を40%減少させます。デバイスを傾けて巨大石の進行方向をコントロールしてください。" />
    <List Id="31036" Txt="アレスの血の渇きが乗り移り、8秒間エリア内の味方部隊に + 20% の攻撃力・攻撃速度・移動速度を与えます。" />
    <List Id="31037" Txt="アレスの血の渇きが乗り移り、9秒間エリア内の味方部隊に + 30% の攻撃力・攻撃速度・移動速度を与えます。" />
    <List Id="31038" Txt="アレスの血の渇きが乗り移り、11秒間エリア内の味方部隊に + 40% の攻撃力・攻撃速度・移動速度を与えます。" />
    <List Id="31039" Txt="アレスの血の渇きが乗り移り、12秒間エリア内の味方部隊に + 50% の攻撃力・攻撃速度・移動速度を与えます。" />
    <List Id="31040" Txt="アレスの血の渇きが乗り移り、15秒間エリア内の味方部隊に + 60% の攻撃力・攻撃速度・移動速度を与えます。" />
    <List Id="31041" Txt="召喚されたフェニックスが10秒間戦場上を飛行することで、通過上にいる味方6部隊をランダムに回復させることができます。ヒーローへの影響はありません。画面上で指をドラッグさせてフェニックスを導いてください。" />
    <List Id="31042" Txt="召喚されたフェニックスが10秒間戦場上を飛行することで、通過上にいる味方12部隊をランダムに回復させることができます。ヒーローへの影響はありません。画面上で指をドラッグさせてフェニックスを導いてください。" />
    <List Id="31043" Txt="召喚されたフェニックスが10秒間戦場上を飛行することで、通過上にいる味方18部隊をランダムに回復させることができます。ヒーローへの影響はありません。画面上で指をドラッグさせてフェニックスを導いてください。" />
    <List Id="31044" Txt="召喚されたフェニックスが10秒間戦場上を飛行することで、通過上にいる味方24部隊をランダムに回復させることができます。ヒーローへの影響はありません。画面上で指をドラッグさせてフェニックスを導いてください。" />
    <List Id="31045" Txt="召喚されたフェニックスが10秒間戦場上を飛行することで、通過上にいる味方30部隊をランダムに回復させることができます。ヒーローへの影響はありません。画面上で指をドラッグさせてフェニックスを導いてください。" />
    <List Id="31046" Txt="エリアを吹雪で覆うことで、エリア内の全敵部隊に最大 HP の6% + 200のダメージを与えます。さらに、6秒間影響下にある部隊を凍結させます。" />
    <List Id="31047" Txt="エリアを吹雪で覆うことで、エリア内の全敵部隊に最大 HP の7% + 400のダメージを与えます。さらに、7秒間影響下にある部隊を凍結させます。" />
    <List Id="31048" Txt="エリアを吹雪で覆うことで、エリア内の全敵部隊に最大 HP の8% + 600のダメージを与えます。さらに、9秒間影響下にある部隊を凍結させます。" />
    <List Id="31049" Txt="エリアを吹雪で覆うことで、エリア内の全敵部隊に最大 HP の9% + 800のダメージを与えます。さらに、11秒間影響下にある部隊を凍結させます。" />
    <List Id="31050" Txt="エリアを吹雪で覆うことで、エリア内の全敵部隊に最大 HP の10% + 1,000のダメージを与えます。さらに、13秒間影響下にある部隊を凍結させます。" />
  </Text>
  <Text Type="6" TypeTxt="任务标题">
    <List Id="32001" Txt="町の館" />
    <List Id="32002" Txt="ゴールドの山" />
    <List Id="32003" Txt="マナの隠し場所" />
    <List Id="32004" Txt="迫り来る戦士たち" />
    <List Id="32005" Txt="ゴールド王" />
    <List Id="32006" Txt="マナ王" />
    <List Id="32007" Txt="ミッション・ポッシブル" />
    <List Id="32008" Txt="完全主義者" />
    <List Id="32009" Txt="勝利の勇気" />
    <List Id="32010" Txt="敗北の運命" />
    <List Id="32011" Txt="アベンジャーズ" />
    <List Id="32012" Txt="アイ・アム・レジェンド" />
    <List Id="32013" Txt="大混雑！" />
    <List Id="32014" Txt="権力への道" />
    <List Id="32015" Txt="邪魔者はいない" />
    <List Id="32016" Txt="不屈" />
    <List Id="32017" Txt="嗚呼！" />
    <List Id="32018" Txt="魔法支配" />
    <List Id="32019" Txt="世界一のファン" />
    <List Id="32020" Txt="バトルの栄光" />
    <List Id="32021" Txt="寂しかった？" />
  </Text>
  <Text Type="7" TypeTxt="任务描述">
    <List Id="33001" Txt="町の館がレベル4に達しました。" />
    <List Id="33002" Txt="町の館がレベル12に達しました。" />
    <List Id="33003" Txt="町の館がレベル20に達しました。" />
    <List Id="33004" Txt="ゴールド貯蔵庫がレベル4に達しました。" />
    <List Id="33005" Txt="ゴールド貯蔵庫がレベル12に達しました。" />
    <List Id="33006" Txt="ゴールド貯蔵庫がレベル20に達しました。" />
    <List Id="33007" Txt="マナ貯蔵庫がレベル4に達しました。" />
    <List Id="33008" Txt="マナ貯蔵庫がレベル12に達しました。" />
    <List Id="33009" Txt="マナ貯蔵庫がレベル20に達しました。" />
    <List Id="33010" Txt="1,000マイトに達しました。" />
    <List Id="33011" Txt="15,000マイトに達しました。" />
    <List Id="33012" Txt="35,000マイトに達しました。" />
    <List Id="33013" Txt="計100,000ゴールドを収集。" />
    <List Id="33014" Txt="計5,000,000ゴールドを収集。" />
    <List Id="33015" Txt="計20,000,000ゴールドを収集。" />
    <List Id="33016" Txt="計100,000マナを収集。" />
    <List Id="33017" Txt="計5,000,000マナを収集。" />
    <List Id="33018" Txt="計20,000,000マナを収集。" />
    <List Id="33019" Txt="5ダンジョンをクリア。" />
    <List Id="33020" Txt="50ダンジョンをクリア。" />
    <List Id="33021" Txt="100ダンジョンをクリア。" />
    <List Id="33022" Txt="10ダンジョンで3スターを獲得。" />
    <List Id="33023" Txt="50ダンジョンで3スターを獲得。" />
    <List Id="33024" Txt="100ダンジョンで3スターを獲得。" />
    <List Id="33025" Txt="他のプレイヤーに対して20攻撃の勝利。" />
    <List Id="33026" Txt="他のプレイヤーに対して200攻撃の勝利。" />
    <List Id="33027" Txt="他のプレイヤーに対して1,000攻撃の勝利。" />
    <List Id="33028" Txt="他のプレイヤーに対して20攻撃の敗北。" />
    <List Id="33029" Txt="他のプレイヤーに対して200攻撃の敗北。" />
    <List Id="33030" Txt="他のプレイヤーに対して1,000攻撃の敗北。" />
    <List Id="33031" Txt="3スターのヒーローを獲得。" />
    <List Id="33032" Txt="6スターのヒーローを獲得。" />
    <List Id="33033" Txt="9スターのヒーローを獲得。" />
    <List Id="33034" Txt="5スターの部隊を所有。" />
    <List Id="33035" Txt="5スターの部隊を6種類所有。" />
    <List Id="33036" Txt="5スターの部隊を12種類所有。" />
    <List Id="33037" Txt="2種類の部隊を所有。" />
    <List Id="33038" Txt="6種類の部隊を所有。" />
    <List Id="33039" Txt="12種類の部隊を所有。" />
    <List Id="33040" Txt="5の障害物をクリア。" />
    <List Id="33041" Txt="15の障害物をクリア。" />
    <List Id="33042" Txt="30の障害物をクリア。" />
    <List Id="33043" Txt="急襲にて100の城壁を破壊。" />
    <List Id="33044" Txt="急襲にて800の城壁を破壊。" />
    <List Id="33045" Txt="急襲にて3,000の城壁を破壊。" />
    <List Id="33046" Txt="10の闘技場バトルで勝利。" />
    <List Id="33047" Txt="200の闘技場バトルで勝利。" />
    <List Id="33048" Txt="1,000の闘技場バトルで勝利。" />
    <List Id="33049" Txt="10の闘技場バトルで敗北。" />
    <List Id="33050" Txt="200の闘技場バトルで敗北。" />
    <List Id="33051" Txt="1,000の闘技場バトルで敗北。" />
    <List Id="33052" Txt="4種類の呪文をアンロック。" />
    <List Id="33053" Txt="8種類の呪文をアンロック。" />
    <List Id="33054" Txt="10種類の呪文をアンロック。" />
    <List Id="33055" Txt="50のヒーローの欠片をダンジョンで獲得。" />
    <List Id="33056" Txt="200のヒーローの欠片をダンジョンで獲得。" />
    <List Id="33057" Txt="1,000のヒーローの欠片をダンジョンで獲得。" />
    <List Id="33058" Txt="5,000の栄光ポイントを獲得。" />
    <List Id="33059" Txt="200,000の栄光ポイントを獲得。" />
    <List Id="33060" Txt="1,000,000の栄光ポイントを獲得。" />
    <List Id="33061" Txt="7日間ログイン。" />
    <List Id="33062" Txt="30日間ログイン。" />
    <List Id="33063" Txt="90日間ログイン。" />
    <List Id="33064" Txt="ログイン報酬！" />
    <List Id="33065" Txt="闘技場で戦闘！" />
    <List Id="33066" Txt="他のプレイヤーからゴールドを強奪！" />
    <List Id="33067" Txt="他のプレイヤーからマナを強奪！" />
    <List Id="33068" Txt="230個の購入で、3000栄光ポイント贈り！" />
    <List Id="33069" Txt="600個の購入で、10000栄光ポイント贈り！" />
    <List Id="33070" Txt="3000個の購入で、20000栄光ポイント贈り！" />
    <List Id="33071" Txt="15000個の購入で、30000栄光ポイント贈り！" />
    <List Id="33072" Txt="50000個の購入で、50000栄光ポイント贈り！" />
  </Text>
  <Text Type="8" TypeTxt="兵种名称">
    <List Id="50001" Txt="ガーディアン" />
    <List Id="50002" Txt="ハンター" />
    <List Id="50003" Txt="パイロマンサー" />
    <List Id="50004" Txt="トレアント" />
    <List Id="50005" Txt="ハンマードワーフ" />
    <List Id="50006" Txt="ケンタウルス" />
    <List Id="50007" Txt="グリフィン" />
    <List Id="50008" Txt="メカマン" />
    <List Id="50009" Txt="サベージオーガ" />
    <List Id="50010" Txt="ショットガンドワーフ" />
    <List Id="50011" Txt="フェアリードラゴン" />
    <List Id="50012" Txt="オーニソプター" />
  </Text>
  <Text Type="9" TypeTxt="兵种描述">
    <List Id="60001" Txt="もっとも基本的でもっとも忠実な戦士。このガーディアンには、死の恐怖など存在しない。訓練には最低限のコストを要するが、軍隊にとっては必要不可欠な要員である。" />
    <List Id="60002" Txt="離れたところから攻撃を仕掛ける「死神」。敵が空中か地上に関わらず、命を失う恐怖を味わうことは避けられないだろう。　" />
    <List Id="60003" Txt="火の奥義を握っているパイロマンサーが現れたら相手の災難になる。十分の安全距離を保てば、一組のパイロマンサーだけでも基地を徹底的に破壊できる。" />
    <List Id="60004" Txt="無限の力を持つ森の戦士。決してそのゆっくりとした動作に惑わされてはいけない。防御の塔の前で今まで体験したことのない恐怖を見せる。　" />
    <List Id="60005" Txt="ドワーフのゴールドに対する欲は止められない。　ゴールドがそこにある限り、邪魔するものはすべてなぎ倒し突き進むだろう。　" />
    <List Id="60006" Txt="他の森の住人たちから敬意を払われている。レンジャーたちは組織化され、団結された軍隊である。彼らの射撃スキルと精度をもってして、怒らせたら最後、命はない！" />
    <List Id="60007" Txt="ドラゴンたちがこの世に君臨する以前に空を制していたのは、このグリフィンたちだった。　血に飢えた猛獣たちは目に入る不愉快なものすべてを血祭りにあげるだろう。　" />
    <List Id="60008" Txt="謎だらけである。この巨人たちがどこから来たのか、鎧の下に何が隠されているのか、知る者はいない。分っているのは、彼らは不屈の残酷さをもって攻撃するということ！" />
    <List Id="60009" Txt="血への貪欲な渇望を持ち、本質的に頑強で強欲。　荒野に揺ぎなく立ち続ける彼らは、恐ろしく凶暴な者をもただの人にしてしまう。　" />
    <List Id="60010" Txt="以前止めることができなかったドワーフたちは、銃器を使用することでさらに抑えられなくなり、ヒーローたちの権威に挑まんとしている。　" />
    <List Id="60011" Txt="ドラゴンがどれだけ念入りに朝の歯磨きをするかに関係なく、すべてを完全に破壊するには、たった一息吹きかけるだけで十分。　" />
    <List Id="60012" Txt="技術革新の結晶。敵は「あれはなんだ？」と空を見上げ目を凝らすまでもなく、粉々にされるだろう。　" />
    <List Id="60013" Txt="部隊の詳細" />
    <List Id="60014" Txt="レベルアップするには部隊のアイコンをタップ" />
    <List Id="60015" Txt="レベル %d" />
    <List Id="60016" Txt="レベル (%d - %d)" />
    <List Id="60017" Txt="雇用したい部隊をタップして開始。" />
    <List Id="60018" Txt="雇用する (%d/%d)" />
    <List Id="60019" Txt="列はいっぱいです。これ以上多くの部隊を訓練することはできません。" />
    <List Id="60020" Txt="キャンプはいっぱいです。この訓練を完了できません。" />
    <List Id="60021" Txt="レベルアップコスト" />
    <List Id="60022" Txt="いっぱい" />
    <List Id="60023" Txt="空" />
    <List Id="60024" Txt="今すぐ戦う" />
    <List Id="60101" Txt="ノーマル" />
    <List Id="60102" Txt="射撃" />
    <List Id="60103" Txt="魔法" />
    <List Id="60104" Txt="破壊" />
    <List Id="60105" Txt="英雄" />
    <List Id="60106" Txt="ライトアーマー" />
    <List Id="60107" Txt="ミディアムアーマー" />
    <List Id="60108" Txt="ヘビーアーマー" />
    <List Id="60109" Txt="建築アーマー" />
    <List Id="60110" Txt="英雄アーマー" />
    <List Id="60111" Txt="ライトアーマーに %d%% のダメージを与えます。" />
    <List Id="60112" Txt="ミディアムアーマーに %d%% のダメージを与えます。" />
    <List Id="60113" Txt="ヘビーアーマーに %d%% のダメージを与えます。" />
    <List Id="60114" Txt="建築アーマーに %d%% のダメージを与えます。" />
    <List Id="60115" Txt="英雄アーマーに %d%% のダメージを与えます。" />
    <List Id="60121" Txt="ランダムターゲット" />
    <List Id="60122" Txt="部隊" />
    <List Id="60123" Txt="ヒーロー" />
    <List Id="60124" Txt="資源の建物" />
    <List Id="60125" Txt="防御の建物" />
    <List Id="60126" Txt="城壁" />
    <List Id="60127" Txt="ランダム建物" />
    <List Id="60128" Txt="空中ターゲット" />
    <List Id="60131" Txt="地上" />
    <List Id="60132" Txt="空中" />
    <List Id="60133" Txt="地上&amp;空中" />
    <List Id="60134" Txt="攻撃の種類： %s" />
    <List Id="60135" Txt="アーマーの種類： %s" />
    <List Id="60201" Txt="ダメージ：" />
    <List Id="60202" Txt="HP：" />
    <List Id="60203" Txt="雇用コスト：" />
    <List Id="60204" Txt="優先ターゲット：" />
    <List Id="60205" Txt="ターゲット：" />
    <List Id="60206" Txt="使用スペース：" />
    <List Id="60207" Txt="雇用時間：" />
    <List Id="60208" Txt="移動スピート：" />
    <List Id="60209" Txt="ダメージ情報" />
    <List Id="60301" Txt="防御設定" />
    <List Id="60302" Txt="ランキング" />
    <List Id="60303" Txt="報酬" />
    <List Id="60304" Txt="%s 前に %s を倒しランクが %s 上がりました！" />
    <List Id="60305" Txt="%s 前に %s に倒されました。ランクが %s 下がりました。" />
    <List Id="60306" Txt="%s 前にチャレンジした際 %s に倒されました。ランクに変動はありません。" />
    <List Id="60307" Txt="%s 前にチャレンジされた際 %s に倒されていません。ランクに変動はありません。" />
    <List Id="60308" Txt="リセット" />
    <List Id="60309" Txt="設定完了！" />
    <List Id="60310" Txt="最低限ヒーロー1名が必要です" />
    <List Id="60311" Txt="上限数に達しているため、これ以上ヒーローを選択できません。" />
    <List Id="60312" Txt="バトルチャンスは使い切りました。" />
    <List Id="60313" Txt="バトルチャンス数：" />
    <List Id="60314" Txt="カウントダウン：" />
    <List Id="60315" Txt="チャレンジ" />
    <List Id="60316" Txt="栄光ポイント +%d" />
    <List Id="60317" Txt="栄光ポイント +%d" />
    <List Id="60318" Txt="現在チャレンジされているため、チャレンジできません。" />
    <List Id="60319" Txt="ターゲットがバトル中のため、チャレンジできません。" />
    <List Id="60501" Txt="%s を レベル %d へ訓練する。" />
    <List Id="60502" Txt="条件を開く" />
    <List Id="60503" Txt="まだアンロックされていません。訓練場へアップデートしに行きますか？" />
  </Text>
  <Text Type="10" TypeTxt="英雄名称">
    <List Id="70201" Txt="騎士パラディン" />
    <List Id="70211" Txt="処刑人" />
    <List Id="70221" Txt="聖霊魔術師" />
    <List Id="70231" Txt="忍者" />
    <List Id="70241" Txt="天使" />
    <List Id="70301" Txt="アサシン" />
    <List Id="70311" Txt="マークスマン" />
    <List Id="70321" Txt="狼男" />
    <List Id="70331" Txt="ヒルジャイアント" />
    <List Id="70341" Txt="サキュバス" />
    <List Id="70401" Txt="エンジニア" />
    <List Id="70411" Txt="氷の魔女" />
    <List Id="70421" Txt="チャンピオン" />
    <List Id="70431" Txt="シクロプス" />
    <List Id="70441" Txt="ドリュアス" />
    <List Id="70451" Txt="ペインダ" />
    <List Id="70461" Txt="シャーマン" />
    <List Id="70471" Txt="ドルイド" />
    <List Id="70481" Txt="錬金術師" />
    <List Id="70491" Txt="略奪者" />
    <List Id="70501" Txt="スライム" />
    <List Id="70502" Txt="クリスタルウーズ" />
    <List Id="70503" Txt="ゼラチンチャンピオン" />
    <List Id="70504" Txt="セントー戦士" />
    <List Id="70505" Txt="セントー・エリート" />
    <List Id="70506" Txt="セントー・キング" />
    <List Id="70511" Txt="サーペント女王" />
    <List Id="70521" Txt="サンダー・ゴッド" />
    <List Id="70541" Txt="ミノタウロスの族長" />
    <List Id="70561" Txt="アイス悪魔" />
    <List Id="70581" Txt="死神" />
    <List Id="70601" Txt="かぼちゃ公爵" />
  </Text>
  <Text Type="11" TypeTxt="英雄技能">
    <List Id="75001" Txt="神聖なる盾" />
    <List Id="75011" Txt="復活" />
    <List Id="75021" Txt="猛撃" />
    <List Id="75031" Txt="強打" />
    <List Id="75041" Txt="魔法のミサイル" />
    <List Id="75051" Txt="神秘の術" />
    <List Id="75061" Txt="抜刀斬" />
    <List Id="75071" Txt="影の武士" />
    <List Id="75081" Txt="回復" />
    <List Id="75091" Txt="飛行" />
    <List Id="75101" Txt="暗殺" />
    <List Id="75111" Txt="陽炎" />
    <List Id="75121" Txt="分裂矢" />
    <List Id="75131" Txt="致死的ショット" />
    <List Id="75141" Txt="憤激" />
    <List Id="75151" Txt="ライフヒル" />
    <List Id="75161" Txt="稲妻" />
    <List Id="75171" Txt="エネルギーショック" />
    <List Id="75181" Txt="死のラッシュ" />
    <List Id="75191" Txt="運命の振り子" />
    <List Id="75201" Txt="熔岩ブラスト" />
    <List Id="75211" Txt="炎の盾" />
    <List Id="75221" Txt="氷の突撃" />
    <List Id="75231" Txt="氷の強襲" />
    <List Id="75241" Txt="嵐のハンマー" />
    <List Id="75251" Txt="電撃" />
    <List Id="75261" Txt="衝撃波" />
    <List Id="75271" Txt="報復" />
    <List Id="75281" Txt="拘束" />
    <List Id="75291" Txt="飛行" />
    <List Id="75301" Txt="投石" />
    <List Id="75311" Txt="緑のアザミ" />
    <List Id="75321" Txt="呪い" />
    <List Id="75331" Txt="デストーテム" />
    <List Id="75341" Txt="エネルギッシュ" />
    <List Id="75351" Txt="絡み合い" />
    <List Id="75361" Txt="秘術投与" />
    <List Id="75371" Txt="錬金術師の火" />
    <List Id="75381" Txt="武装準備" />
    <List Id="75391" Txt="破壊" />
    <List Id="75401" Txt="毒ミスト" />
    <List Id="75421" Txt="雷雨" />
    <List Id="75441" Txt="カーニバル" />
    <List Id="75461" Txt="化身" />
    <List Id="75481" Txt="魂を刈取る。" />
    <List Id="75501" Txt="アイスフォグ" />
    <List Id="85001" Txt="回復" />
    <List Id="85011" Txt="猛烈な一撃" />
    <List Id="85021" Txt="活性化" />
    <List Id="85031" Txt="焼き払う" />
    <List Id="85041" Txt="自己破壊" />
    <List Id="85051" Txt="破壊的攻撃" />
    <List Id="85061" Txt="火炎防御" />
    <List Id="85071" Txt="剣の甲" />
    <List Id="85081" Txt="拡散" />
    <List Id="85091" Txt="スローダウン" />
    <List Id="85101" Txt="衰弱" />
    <List Id="85111" Txt="凶暴" />
    <List Id="85121" Txt="ストーンスキン" />
    <List Id="85131" Txt="戦神" />
    <List Id="85141" Txt="執念" />
    <List Id="85511" Txt="衝撃波" />
    <List Id="85521" Txt="矛戟投げ" />
    <List Id="85531" Txt="戦争踏み" />
  </Text>
  <Text Type="12" TypeTxt="技能描述">
    <List Id="80001" Txt="防御を強化します。5秒間受けるダメージが40%減少されます。" />
    <List Id="80002" Txt="防御を強化します。5秒間受けるダメージが50%減少されます。" />
    <List Id="80003" Txt="防御を強化します。5秒間受けるダメージが60%減少されます。" />
    <List Id="80004" Txt="防御を強化します。5秒間受けるダメージが65%減少されます。" />
    <List Id="80005" Txt="防御を強化します。5秒間受けるダメージが70%減少されます。" />
    <List Id="80006" Txt="防御を強化します。5秒間受けるダメージが75%減少されます。" />
    <List Id="80007" Txt="防御を強化します。5秒間受けるダメージが80%減少されます。" />
    <List Id="80008" Txt="防御を強化します。5秒間受けるダメージが85%減少されます。" />
    <List Id="80009" Txt="防御を強化します。5秒間受けるダメージが90%減少されます。" />
    <List Id="80021" Txt="ターゲットに100%のダメージを与え、1秒間昏睡させます。" />
    <List Id="80022" Txt="ターゲットに150%のダメージを与え、1秒間昏睡させます。" />
    <List Id="80023" Txt="ターゲットに200%のダメージを与え、1秒間昏睡させます。" />
    <List Id="80024" Txt="ターゲットに220%のダメージを与え、2秒間昏睡させます。" />
    <List Id="80025" Txt="ターゲットに250%のダメージを与え、2秒間昏睡させます。" />
    <List Id="80026" Txt="ターゲットに280%のダメージを与え、2秒間昏睡させます。" />
    <List Id="80027" Txt="ターゲットに300%のダメージを与え、3秒間昏睡させます。" />
    <List Id="80028" Txt="ターゲットに330%のダメージを与え、3秒間昏睡させます。" />
    <List Id="80029" Txt="ターゲットに360%のダメージを与え、3秒間昏睡させます。" />
    <List Id="80041" Txt="付近の2ターゲットに200%のダメージを与えます。" />
    <List Id="80042" Txt="付近の3ターゲットに220%のダメージを与えます。" />
    <List Id="80043" Txt="付近の4ターゲットに240%のダメージを与えます。" />
    <List Id="80044" Txt="付近の5ターゲットに260%のダメージを与えます。" />
    <List Id="80045" Txt="付近の6ターゲットに280%のダメージを与えます。" />
    <List Id="80046" Txt="付近の7ターゲットに300%のダメージを与えます。" />
    <List Id="80047" Txt="付近の8ターゲットに320%のダメージを与えます。" />
    <List Id="80048" Txt="付近の9ターゲットに340%のダメージを与えます。" />
    <List Id="80049" Txt="付近の10ターゲットに360%のダメージを与えます。" />
    <List Id="80061" Txt="ターゲットに300%のダメージを与えます。" />
    <List Id="80062" Txt="ターゲットに400%のダメージを与えます。" />
    <List Id="80063" Txt="ターゲットに450%のダメージを与えます。" />
    <List Id="80064" Txt="ターゲットに500%のダメージを与えます。" />
    <List Id="80065" Txt="ターゲットに550%のダメージを与えます。" />
    <List Id="80066" Txt="ターゲットに600%のダメージを与えます。" />
    <List Id="80067" Txt="ターゲットに650%のダメージを与えます。" />
    <List Id="80068" Txt="ターゲットに700%のダメージを与えます。" />
    <List Id="80069" Txt="ターゲットに750%のダメージを与えます。" />
    <List Id="80081" Txt="味方部隊の HP を攻撃値の200%復元します。" />
    <List Id="80082" Txt="味方部隊の HP を攻撃値の230%復元します。" />
    <List Id="80083" Txt="味方部隊の HP を攻撃値の260%復元します。" />
    <List Id="80084" Txt="味方部隊の HP を攻撃値の290%復元します。" />
    <List Id="80085" Txt="味方部隊の HP を攻撃値の320%復元します。" />
    <List Id="80086" Txt="味方部隊の HP を攻撃値の350%復元します。" />
    <List Id="80087" Txt="味方部隊の HP を攻撃値の380%復元します。" />
    <List Id="80088" Txt="味方部隊の HP を攻撃値の410%復元します。" />
    <List Id="80089" Txt="味方部隊の HP を攻撃値の440%復元します。" />
    <List Id="80101" Txt="最低 HP のターゲットに250%のダメージを与えます。" />
    <List Id="80102" Txt="最低 HP のターゲットに300%のダメージを与えます。" />
    <List Id="80103" Txt="最低 HP のターゲットに330%のダメージを与えます。" />
    <List Id="80104" Txt="最低 HP のターゲットに360%のダメージを与えます。" />
    <List Id="80105" Txt="最低 HP のターゲットに390%のダメージを与えます。" />
    <List Id="80106" Txt="最低 HP のターゲットに420%のダメージを与えます。" />
    <List Id="80107" Txt="最低 HP のターゲットに450%のダメージを与えます。" />
    <List Id="80108" Txt="最低 HP のターゲットに480%のダメージを与えます。" />
    <List Id="80109" Txt="最低 HP のターゲットに510%のダメージを与えます。" />
    <List Id="80121" Txt="付近の3ターゲットに130%のダメージを与えます。" />
    <List Id="80122" Txt="付近の3ターゲットに180%のダメージを与えます。" />
    <List Id="80123" Txt="付近の3ターゲットに210%のダメージを与えます。" />
    <List Id="80124" Txt="付近の3ターゲットに240%のダメージを与えます。" />
    <List Id="80125" Txt="付近の3ターゲットに270%のダメージを与えます。" />
    <List Id="80126" Txt="付近の3ターゲットに300%のダメージを与えます。" />
    <List Id="80127" Txt="付近の3ターゲットに330%のダメージを与えます。" />
    <List Id="80128" Txt="付近の3ターゲットに360%のダメージを与えます。" />
    <List Id="80129" Txt="付近の3ターゲットに390%のダメージを与えます。" />
    <List Id="80141" Txt="5秒間攻撃力が30%増加します。" />
    <List Id="80142" Txt="5秒間攻撃力が50%増加します。" />
    <List Id="80143" Txt="5秒間攻撃力が70%増加します。" />
    <List Id="80144" Txt="6秒間攻撃力が80%増加します。" />
    <List Id="80145" Txt="6秒間攻撃力が110%増加します。" />
    <List Id="80146" Txt="6秒間攻撃力が120%増加します。" />
    <List Id="80147" Txt="7秒間攻撃力が130%増加します。" />
    <List Id="80148" Txt="7秒間攻撃力が150%増加します。" />
    <List Id="80149" Txt="7秒間攻撃力が170%増加します。" />
    <List Id="80161" Txt="周囲の全敵部隊に150%のダメージを与えます。" />
    <List Id="80162" Txt="周囲の全敵部隊に200%のダメージを与えます。" />
    <List Id="80163" Txt="周囲の全敵部隊に230%のダメージを与えます。" />
    <List Id="80164" Txt="周囲の全敵部隊に250%のダメージを与えます。" />
    <List Id="80165" Txt="周囲の全敵部隊に270%のダメージを与えます。" />
    <List Id="80166" Txt="周囲の全敵部隊に290%のダメージを与えます。" />
    <List Id="80167" Txt="周囲の全敵部隊に310%のダメージを与えます。" />
    <List Id="80168" Txt="周囲の全敵部隊に330%のダメージを与えます。" />
    <List Id="80169" Txt="周囲の全敵部隊に350%のダメージを与えます。" />
    <List Id="80181" Txt="5秒間単体ターゲットに最大 HPの15％を減らし、攻撃力の15%も下げさせます。" />
    <List Id="80182" Txt="5秒間単体ターゲットに最大 HPの20％を減らし、攻撃力の20%も下げさせます。" />
    <List Id="80183" Txt="5秒間単体ターゲットに最大 HPの23％を減らし、攻撃力の23%も下げさせます。" />
    <List Id="80184" Txt="6秒間単体ターゲットに最大 HPの26％を減らし、攻撃力の24%も下げさせます。" />
    <List Id="80185" Txt="6秒間単体ターゲットに最大 HPの29％を減らし、攻撃力の27%も下げさせます。" />
    <List Id="80186" Txt="6秒間単体ターゲットに最大 HPの32％を減らし、攻撃力の30%も下げさせます。" />
    <List Id="80187" Txt="7秒間単体ターゲットに最大 HPの35％を減らし、攻撃力の31%も下げさせます。" />
    <List Id="80188" Txt="7秒間単体ターゲットに最大 HPの38％を減らし、攻撃力の34%も下げさせます。" />
    <List Id="80189" Txt="7秒間単体ターゲットに最大 HPの41％を減らし、攻撃力の37%も下げさせます。" />
    <List Id="80201" Txt="エリア内全敵部隊に110%のダメージを与えます。" />
    <List Id="80202" Txt="エリア内全敵部隊に150%のダメージを与えます。" />
    <List Id="80203" Txt="エリア内全敵部隊に170%のダメージを与えます。" />
    <List Id="80204" Txt="エリア内全敵部隊に190%のダメージを与えます。" />
    <List Id="80205" Txt="エリア内全敵部隊に210%のダメージを与えます。" />
    <List Id="80206" Txt="エリア内全敵部隊に230%のダメージを与えます。" />
    <List Id="80207" Txt="エリア内全敵部隊に250%のダメージを与えます。" />
    <List Id="80208" Txt="エリア内全敵部隊に270%のダメージを与えます。" />
    <List Id="80209" Txt="エリア内全敵部隊に290%のダメージを与えます。" />
    <List Id="80221" Txt="ターゲットに150%のダメージを与え、6秒間攻撃速度と移動速度を10%減少させます。" />
    <List Id="80222" Txt="ターゲットに200%のダメージを与え、6秒間攻撃スピードと移動スピードを15%減少させます。" />
    <List Id="80223" Txt="ターゲットに230%のダメージを与え、6秒間攻撃スピードと移動スピードを17%減少させます。" />
    <List Id="80224" Txt="ターゲットに240%のダメージを与え、7秒間攻撃スピードと移動スピードを18%減少させます。" />
    <List Id="80225" Txt="ターゲットに260%のダメージを与え、7秒間攻撃スピードと移動スピードを20%減少させます。" />
    <List Id="80226" Txt="ターゲットに280%のダメージを与え、7秒間攻撃スピードと移動スピードを22%減少させます。" />
    <List Id="80227" Txt="ターゲットに290%のダメージを与え、8秒間攻撃スピードと移動スピードを23%減少させます。" />
    <List Id="80228" Txt="ターゲットに310%のダメージを与え、8秒間攻撃スピードと移動スピードを25%減少させます。" />
    <List Id="80229" Txt="ターゲットに330%のダメージを与え、8秒間攻撃スピードと移動スピードを27%減少させます。" />
    <List Id="80241" Txt="付近にいる3ターゲットにハンマーを投げ、100%のダメージを与え、3秒間昏睡させます。" />
    <List Id="80242" Txt="付近にいる3ターゲットにハンマーを投げ、150%のダメージを与え、3秒間昏睡させます。" />
    <List Id="80243" Txt="付近にいる3ターゲットにハンマーを投げ、180%のダメージを与え、3秒間昏睡させます。" />
    <List Id="80244" Txt="付近にいる3ターゲットにハンマーを投げ、200%のダメージを与え、3秒間昏睡させます。" />
    <List Id="80245" Txt="付近にいる3ターゲットにハンマーを投げ、220%のダメージを与え、3秒間昏睡させます。" />
    <List Id="80246" Txt="付近にいる3ターゲットにハンマーを投げ、240%のダメージを与え、3秒間昏睡させます。" />
    <List Id="80247" Txt="付近にいる3ターゲットにハンマーを投げ、270%のダメージを与え、3秒間昏睡させます。" />
    <List Id="80248" Txt="付近にいる3ターゲットにハンマーを投げ、290%のダメージを与え、3秒間昏睡させます。" />
    <List Id="80249" Txt="付近にいる3ターゲットにハンマーを投げ、310%のダメージを与え、3秒間昏睡させます。" />
    <List Id="80261" Txt="前方の全敵部隊に100%のダメージを与えます。" />
    <List Id="80262" Txt="前方の全敵部隊に150%のダメージを与えます。" />
    <List Id="80263" Txt="前方の全敵部隊に170%のダメージを与えます。" />
    <List Id="80264" Txt="前方の全敵部隊に190%のダメージを与えます。" />
    <List Id="80265" Txt="前方の全敵部隊に210%のダメージを与えます。" />
    <List Id="80266" Txt="前方の全敵部隊に230%のダメージを与えます。" />
    <List Id="80267" Txt="前方の全敵部隊に250%のダメージを与えます。" />
    <List Id="80268" Txt="前方の全敵部隊に270%のダメージを与えます。" />
    <List Id="80269" Txt="前方の全敵部隊に290%のダメージを与えます。" />
    <List Id="80281" Txt="ターゲットに100%のダメージを与え、1秒間昏睡させます。" />
    <List Id="80282" Txt="ターゲットに150%のダメージを与え、1秒間昏睡させます。" />
    <List Id="80283" Txt="ターゲットに180%のダメージを与え、1秒間昏睡させます。" />
    <List Id="80284" Txt="ターゲットに190%のダメージを与え、2秒間昏睡させます。" />
    <List Id="80285" Txt="ターゲットに220%のダメージを与え、2秒間昏睡させます。" />
    <List Id="80286" Txt="ターゲットに250%のダメージを与え、2秒間昏睡させます。" />
    <List Id="80287" Txt="ターゲットに260%のダメージを与え、3秒間昏睡させます。" />
    <List Id="80288" Txt="ターゲットに290%のダメージを与え、3秒間昏睡させます。" />
    <List Id="80289" Txt="ターゲットに320%のダメージを与え、3秒間昏睡させます。" />
    <List Id="80301" Txt="戦場上でランダムな敵部隊に岩石を投げ、250%のダメージを与えます。" />
    <List Id="80302" Txt="戦場上でランダムな敵部隊に岩石を投げ、320%のダメージを与えます。" />
    <List Id="80303" Txt="戦場上でランダムな敵部隊に岩石を投げ、360%のダメージを与えます。" />
    <List Id="80304" Txt="戦場上でランダムな敵部隊に岩石を投げ、400%のダメージを与えます。" />
    <List Id="80305" Txt="戦場上でランダムな敵部隊に岩石を投げ、440%のダメージを与えます。" />
    <List Id="80306" Txt="戦場上でランダムな敵部隊に岩石を投げ、480%のダメージを与えます。" />
    <List Id="80307" Txt="戦場上でランダムな敵部隊に岩石を投げ、520%のダメージを与えます。" />
    <List Id="80308" Txt="戦場上でランダムな敵部隊に岩石を投げ、560%のダメージを与えます。" />
    <List Id="80309" Txt="戦場上でランダムな敵部隊に岩石を投げ、600%のダメージを与えます。" />
    <List Id="80321" Txt="6秒間ターゲットの攻撃力を25%減少させます。" />
    <List Id="80322" Txt="6秒間ターゲットの攻撃力を35%減少させます。" />
    <List Id="80323" Txt="6秒間ターゲットの攻撃力を42%減少させます。" />
    <List Id="80324" Txt="7秒間ターゲットの攻撃力を44%減少させます。" />
    <List Id="80325" Txt="7秒間ターゲットの攻撃力を48%減少させます。" />
    <List Id="80326" Txt="7秒間ターゲットの攻撃力を52%減少させます。" />
    <List Id="80327" Txt="8秒間ターゲットの攻撃力を54%減少させます。" />
    <List Id="80328" Txt="8秒間ターゲットの攻撃力を57%減少させます。" />
    <List Id="80329" Txt="8秒間ターゲットの攻撃力を60%減少させます。" />
    <List Id="80341" Txt="近くの HP が最も低い味方2部隊の HP を200%復元させ、攻撃力を5秒間15%増加します。" />
    <List Id="80342" Txt="近くの HP が最も低い味方3部隊の HP を210%復元させ、攻撃力を5秒間20%増加します。" />
    <List Id="80343" Txt="近くの HP が最も低い味方4部隊の HP を220%復元させ、攻撃力を5秒間23%増加します。" />
    <List Id="80344" Txt="近くの HP が最も低い味方5部隊の HP を230%復元させ、攻撃力を5秒間25%増加します。" />
    <List Id="80345" Txt="近くの HP が最も低い味方6部隊の HP を240%復元させ、攻撃力を5秒間26%増加します。" />
    <List Id="80346" Txt="近くの HP が最も低い味方7部隊の HP を250%復元させ、攻撃力を5秒間28%増加します。" />
    <List Id="80347" Txt="近くの HP が最も低い味方8部隊の HP を260%復元させ、攻撃力を5秒間29%増加します。" />
    <List Id="80348" Txt="近くの HP が最も低い味方9部隊の HP を270%復元させ、攻撃力を5秒間31%増加します。" />
    <List Id="80349" Txt="近くの HP が最も低い味方10部隊の HP を280%復元させ、攻撃力を5秒間32%増加します。" />
    <List Id="80361" Txt="ターゲットに180%のダメージを与えます。" />
    <List Id="80362" Txt="ターゲットに250%のダメージを与えます。" />
    <List Id="80363" Txt="ターゲットに300%のダメージを与えます。" />
    <List Id="80364" Txt="ターゲットに340%のダメージを与えます。" />
    <List Id="80365" Txt="ターゲットに380%のダメージを与えます。" />
    <List Id="80366" Txt="ターゲットに420%のダメージを与えます。" />
    <List Id="80367" Txt="ターゲットに460%のダメージを与えます。" />
    <List Id="80368" Txt="ターゲットに500%のダメージを与えます。" />
    <List Id="80369" Txt="ターゲットに540%のダメージを与えます。" />
    <List Id="80381" Txt="6秒間受けるダメージが15%減少されます。" />
    <List Id="80382" Txt="6秒間受けるダメージが20%減少されます。" />
    <List Id="80383" Txt="6秒間受けるダメージが23%減少されます。" />
    <List Id="80384" Txt="6秒間受けるダメージが26%減少されます。" />
    <List Id="80385" Txt="6秒間受けるダメージが29%減少されます。" />
    <List Id="80386" Txt="6秒間受けるダメージが32%減少されます。" />
    <List Id="80387" Txt="6秒間受けるダメージが35%減少されます。" />
    <List Id="80388" Txt="6秒間受けるダメージが38%減少されます。" />
    <List Id="80389" Txt="6秒間受けるダメージが41%減少されます。" />
    <List Id="80401" Txt="エリア範囲で全ての敵を中毒させ、6秒内に0.5秒ごとに敵に8％のダメージを増加と15のダメージを与えます。" />
    <List Id="80402" Txt="エリア範囲で全ての敵を中毒させ、6秒内に0.5秒ごとに敵に10％のダメージを増加と25のダメージを与えます。" />
    <List Id="80403" Txt="エリア範囲で全ての敵を中毒させ、6秒内に0.5秒ごとに敵に13％のダメージを増加と35のダメージを与えます。" />
    <List Id="80404" Txt="エリア範囲で全ての敵を中毒させ、6秒内に0.5秒ごとに敵に15％のダメージを増加と45のダメージを与えます。。" />
    <List Id="80405" Txt="エリア範囲で全ての敵を中毒させ、6秒内に0.5秒ごとに敵に18％のダメージを増加と55のダメージを与えます。" />
    <List Id="80406" Txt="エリア範囲で全ての敵を中毒させ、6秒内に0.5秒ごとに敵に20％のダメージを増加と65のダメージを与えます。" />
    <List Id="80407" Txt="エリア範囲で全ての敵を中毒させ、6秒内に0.5秒ごとに敵に23％のダメージを増加と75のダメージを与えます。" />
    <List Id="80408" Txt="エリア範囲で全ての敵を中毒させ、6秒内に0.5秒ごとに敵に25％のダメージを増加と85のダメージを与えます。" />
    <List Id="80409" Txt="エリア範囲で全ての敵を中毒させ、6秒内に0.5秒ごとに敵に28％のダメージを増加と95のダメージを与えます。" />
    <List Id="80421" Txt="一つのランダムな目標に落雷をしたら、目標エリアでの全ての敵に200％のダメージを与える 。また、敵は1.5秒にめまいがする。" />
    <List Id="80422" Txt="一つのランダムな目標に落雷をしたら、目標エリアでの全ての敵に230％のダメージを与える 。また、敵は1.5秒にめまいがする。" />
    <List Id="80423" Txt="一つのランダムな目標に落雷をしたら、目標エリアでの全ての敵に260％のダメージを与える 。また、敵は1.5秒にめまいがする。" />
    <List Id="80424" Txt="一つのランダムな目標に落雷をしたら、目標エリアでの全ての敵に290％の傷を付ける。また、敵は1.5秒にめまいがする。" />
    <List Id="80425" Txt="一つのランダムな目標に落雷をしたら、目標エリアでの全ての敵に320％のダメージを与える 。また、敵は1.5秒にめまいがする。" />
    <List Id="80426" Txt="一つのランダムな目標に落雷をしたら、目標エリアでの全ての敵に350％の傷を付ける。また、敵は1.5秒にめまいがする。" />
    <List Id="80427" Txt="一つのランダムな目標に落雷をしたら、目標エリアでの全ての敵に380％のダメージを与える 。また、敵は1.5秒にめまいがする。" />
    <List Id="80428" Txt="一つのランダムな目標に落雷をしたら、目標エリアでの全ての敵に410％のダメージを与える 。また、敵は1.5秒にめまいがする。" />
    <List Id="80429" Txt="一つのランダムな目標に落雷をしたら、目標エリアでの全ての敵に440％の傷を付ける。また、敵は1.5秒にめまいがする。" />
    <List Id="80441" Txt="8秒間に味方部隊の攻撃力、攻撃スピードや移動スピードを10％アップします。" />
    <List Id="80442" Txt="8秒間に味方部隊の攻撃力、攻撃スピードや移動スピードを15％アップします" />
    <List Id="80443" Txt="8秒間に味方部隊の攻撃力、攻撃スピードや移動スピードを20％アップします" />
    <List Id="80444" Txt="8秒間に味方部隊の攻撃力、攻撃スピードや移動スピードを25％アップします" />
    <List Id="80445" Txt="8秒間に味方部隊の攻撃力、攻撃スピードや移動スピードを30％アップします" />
    <List Id="80446" Txt="8秒間に味方部隊の攻撃力、攻撃スピードや移動スピードを35％アップします" />
    <List Id="80447" Txt="8秒間に味方部隊の攻撃力、攻撃スピードや移動スピードを40％アップします" />
    <List Id="80448" Txt="8秒間に味方部隊の攻撃力、攻撃スピードや移動スピードを45％アップします" />
    <List Id="80449" Txt="8秒間に味方部隊の攻撃力、攻撃スピードや移動スピードを50％アップします" />
    <List Id="80481" Txt="2体の敵のライフポイントの15％を取る。" />
    <List Id="80482" Txt="3体の敵のライフポイントの15％を取る。" />
    <List Id="80483" Txt="4体の敵のライフポイントの15％を取る。" />
    <List Id="80484" Txt="5体の敵のライフポイントの15％を取る。" />
    <List Id="80485" Txt="
6体の敵のライフポイントの15％を取る。" />
    <List Id="80486" Txt="7体の敵のライフポイントの15％を取る。" />
    <List Id="80487" Txt="8体の敵のライフポイントの15％を取る。" />
    <List Id="80488" Txt="9体の敵のライフポイントの15％を取る。" />
    <List Id="80489" Txt="10体の敵のライフポイントの15％を取る。" />
    <List Id="80501" Txt="6秒間にランダムで敵部隊6体の移動スピードを30％マイナスします。" />
    <List Id="80502" Txt="7秒間にランダムで敵部隊8体の移動スピードを35％マイナスします。" />
    <List Id="80503" Txt="8秒間にランダムで敵部隊10体の移動スピードを40％マイナスします。" />
    <List Id="80504" Txt="9秒間にランダムで敵部隊12体の移動スピードを45％マイナスします。" />
    <List Id="80505" Txt="10秒間にランダムで敵部隊14体の移動スピードを50％マイナスします。" />
    <List Id="80506" Txt="11秒間にランダムで敵部隊16体の移動スピードを55％マイナスします。" />
    <List Id="80507" Txt="12秒間にランダムで敵部隊18体の移動スピードを60％マイナスします。" />
    <List Id="80508" Txt="13秒間にランダムで敵部隊20体の移動スピードを65％マイナスします。" />
    <List Id="80509" Txt="14秒間にランダムで敵部隊22体の移動スピードを70％マイナスします。" />
    <List Id="85501" Txt="犠牲" />
    <List Id="85502" Txt="犠牲（中）" />
    <List Id="85503" Txt="犠牲（大）" />
    <List Id="90001" Txt="10%の HP 復元を行い回復させます。" />
    <List Id="90002" Txt="15%の HP 復元を行い回復させます。" />
    <List Id="90003" Txt="20%の HP 復元を行い回復させます。" />
    <List Id="90004" Txt="25%の HP 復元を行い回復させます。" />
    <List Id="90005" Txt="30%の HP 復元を行い回復させます。" />
    <List Id="90011" Txt="攻撃時に1秒間ターゲットを昏睡させるチャンスが10%あります。" />
    <List Id="90012" Txt="攻撃時に1.5秒間ターゲットを昏睡させるチャンスが10%あります。" />
    <List Id="90013" Txt="攻撃時に2秒間ターゲットを昏睡させるチャンスが10%あります。" />
    <List Id="90014" Txt="攻撃時に2.5秒間ターゲットを昏睡させるチャンスが10%あります。" />
    <List Id="90015" Txt="攻撃時に3秒間ターゲットを昏睡させるチャンスが10%あります。" />
    <List Id="90021" Txt="バトル開始時にエネルギーが20%増加します。" />
    <List Id="90022" Txt="バトル開始時にエネルギーが40%増加します。" />
    <List Id="90023" Txt="バトル開始時にエネルギーが60%増加します。" />
    <List Id="90024" Txt="バトル開始時にエネルギーが80%増加します。" />
    <List Id="90025" Txt="バトル開始時にエネルギーが100%増加します。" />
    <List Id="90031" Txt="攻撃を受けた時、受ける全ダメージを無効にするチャンスが5%あります。" />
    <List Id="90032" Txt="攻撃を受けた時、受ける全ダメージを無効にするチャンスが6%あります。" />
    <List Id="90033" Txt="攻撃を受けた時、受ける全ダメージを無効にするチャンスが7%あります。" />
    <List Id="90034" Txt="攻撃を受けた時、受ける全ダメージを無効にするチャンスが8%あります。" />
    <List Id="90035" Txt="攻撃を受けた時、受ける全ダメージを無効にするチャンスが9%あります。" />
    <List Id="90041" Txt="死んだ際に付近の敵部隊に100%のダメージを与えます。" />
    <List Id="90042" Txt="死んだ際に付近の敵部隊に175%のダメージを与えます。" />
    <List Id="90043" Txt="死んだ際に付近の敵部隊に250%のダメージを与えます。" />
    <List Id="90044" Txt="死んだ際に付近の敵部隊に325%のダメージを与えます。" />
    <List Id="90045" Txt="死んだ際に付近の敵部隊に400%のダメージを与えます。" />
    <List Id="90051" Txt="攻撃時に与えるダメージを3倍にするチャンスが10%あります。" />
    <List Id="90052" Txt="攻撃時に与えるダメージを4倍にするチャンスが10%あります。" />
    <List Id="90053" Txt="攻撃時に与えるダメージを5倍にするチャンスが10%あります。" />
    <List Id="90054" Txt="攻撃時に与えるダメージを6倍にするチャンスが10%あります。" />
    <List Id="90055" Txt="攻撃時に与えるダメージを7倍にするチャンスが10%あります。" />
    <List Id="90061" Txt="受けるダメージの8%をかわします。" />
    <List Id="90062" Txt="受けるダメージの11%をかわします。" />
    <List Id="90063" Txt="受けるダメージの14%をかわします。" />
    <List Id="90064" Txt="受けるダメージの17%をかわします。" />
    <List Id="90065" Txt="受けるダメージの20%をかわします。" />
    <List Id="90071" Txt="受けるダメージを100%かわすチャンスが5%あります。" />
    <List Id="90072" Txt="受けるダメージを100%かわすチャンスが6%あります。" />
    <List Id="90073" Txt="受けるダメージを100%かわすチャンスが7%あります。" />
    <List Id="90074" Txt="受けるダメージを100%かわすチャンスが8%あります。" />
    <List Id="90075" Txt="受けるダメージを100%かわすチャンスが9%あります。" />
    <List Id="90081" Txt="攻撃時にターゲットのエネルギーを5減少させます。" />
    <List Id="90082" Txt="攻撃時にターゲットのエネルギーを10減少させます。" />
    <List Id="90083" Txt="攻撃時にターゲットのエネルギーを15減少させます。" />
    <List Id="90084" Txt="攻撃時にターゲットのエネルギーを20減少させます。" />
    <List Id="90085" Txt="攻撃時にターゲットのエネルギーを25減少させます。" />
    <List Id="90091" Txt="攻撃時に5秒間敵部隊の速度を30%減少させるチャンスが25%あります。" />
    <List Id="90092" Txt="攻撃時に5秒間敵部隊の速度を40%減少させるチャンスが25%あります。" />
    <List Id="90093" Txt="攻撃時に5秒間敵部隊の速度を50%減少させるチャンスが25%あります。" />
    <List Id="90094" Txt="攻撃時に5秒間敵部隊の速度を60%減少させるチャンスが25%あります。" />
    <List Id="90095" Txt="攻撃時に5秒間敵部隊の速度を70%減少させるチャンスが25%あります。" />
    <List Id="90101" Txt="移動スピードを10%増加します。" />
    <List Id="90102" Txt="移動スピードを20%増加します。" />
    <List Id="90103" Txt="移動スピードを30%増加します。" />
    <List Id="90104" Txt="移動スピードを40%増加します。" />
    <List Id="90105" Txt="移動スピードを50%増加します。" />
    <List Id="90111" Txt="攻撃スピードを10%増加します。" />
    <List Id="90112" Txt="攻撃スピードを15%増加します。" />
    <List Id="90113" Txt="攻撃スピードを20%増加します。" />
    <List Id="90114" Txt="攻撃スピードを25%増加します。" />
    <List Id="90115" Txt="攻撃スピードを30%増加します。" />
    <List Id="90121" Txt="受けるダメージが5%減少されます。" />
    <List Id="90122" Txt="受けるダメージが10%減少されます。" />
    <List Id="90123" Txt="受けるダメージが15%減少されます。" />
    <List Id="90124" Txt="受けるダメージが20%減少されます。" />
    <List Id="90125" Txt="受けるダメージが25%減少されます。" />
    <List Id="90131" Txt="攻撃力が10%増加します。" />
    <List Id="90132" Txt="攻撃力が15%増加します。" />
    <List Id="90133" Txt="攻撃力が20%増加します。" />
    <List Id="90134" Txt="攻撃力が25%増加します。" />
    <List Id="90135" Txt="攻撃力が30%増加します。" />
    <List Id="90141" Txt="HP が10%増加します。" />
    <List Id="90142" Txt="HP が15%増加します。" />
    <List Id="90143" Txt="HP が20%増加します。" />
    <List Id="90144" Txt="HP が25%増加します。" />
    <List Id="90145" Txt="HP が30%増加します。" />
    <List Id="91000" Txt="（才能の更新には300宝石を要します）" />
    <List Id="91001" Txt="新しいヒーロースロットをアンロックしますか？" />
    <List Id="91002" Txt="ヒーロー雇用の追加にはさらにコストがかかります。雇用コストは翌日、基本額（500）に戻ります。" />
    <List Id="91003" Txt="ヒーロースロット数が上限に達しました。" />
    <List Id="91501" Txt="犠牲になっている時、100スキル経験値が与えられます。" />
    <List Id="91502" Txt="犠牲になっている時、600スキル経験値が与えられます。" />
    <List Id="91503" Txt="犠牲になっている時、3,000スキル経験値が与えられます。" />
    <List Id="91511" Txt="確率25％で衝撃波を発動でき、前方全ての敵に250％ダメージを与える" />
    <List Id="91521" Txt="確率25％で魔法飛弾を発動でき、前方の敵5体に250％ダメージを与える" />
    <List Id="91531" Txt="
確率25％でヒーロー5体に250％ダメージを与えて、2秒間に昏睡させる。" />
  </Text>
  <Text Type="13" TypeTxt="名稱">
    <List Id="34001" Txt="ダンジョン 1" />
    <List Id="34002" Txt="ダンジョン 2" />
    <List Id="34003" Txt="ダンジョン 3" />
    <List Id="34004" Txt="ダンジョン 4" />
    <List Id="34005" Txt="ダンジョン 5" />
    <List Id="34006" Txt="ダンジョン 6" />
    <List Id="34007" Txt="ダンジョン 7" />
    <List Id="34008" Txt="ダンジョン 8" />
    <List Id="34009" Txt="達成" />
    <List Id="34010" Txt="完了：" />
    <List Id="34011" Txt="呪文" />
    <List Id="34012" Txt="リサーチ時間" />
    <List Id="34013" Txt="ダンジョン" />
    <List Id="34014" Txt="スカルマークのついたダンジョンでは、ヒーローの欠片を見つけるチャンスが高めです！" />
    <List Id="34015" Txt="ヒーローの変更" />
    <List Id="34016" Txt="建物レベル %d でアンロックします！" />
    <List Id="34017" Txt="この呪文はすでに所有しています！" />
    <List Id="34018" Txt="いっぱい" />
    <List Id="34019" Txt="もっとプレイする！" />
    <List Id="34020" Txt="%dの宝石を使って、ダンジョン5回を購入できます。" />
    <List Id="34021" Txt="ダメージ HP：" />
    <List Id="34022" Txt="復元されたダメージ：" />
    <List Id="34023" Txt="回復 HP：" />
    <List Id="34024" Txt="復元された回復：" />
    <List Id="34025" Txt="増加攻撃力：" />
    <List Id="34026" Txt="魔法持続時間：" />
    <List Id="34027" Txt="建物のダメージ：" />
    <List Id="34028" Txt="復元された建物のダメージ：" />
    <List Id="34029" Txt="効果持続時間：" />
    <List Id="34030" Txt="減少 HP：" />
    <List Id="34031" Txt="継続ダメージ：" />
    <List Id="34032" Txt="減少攻撃力：" />
    <List Id="34033" Txt="攻撃速度：" />
    <List Id="34034" Txt="移動速度：" />
    <List Id="34035" Txt="回復数：" />
    <List Id="34036" Txt="効果持続時間：" />
    <List Id="34037" Txt="無敵の部隊：" />
    <List Id="34038" Txt="魔法効果：" />
    <List Id="34039" Txt="Google+ で推奨されました" />
    <List Id="34040" Txt="お気に入りなら評価下さい!" />
    <List Id="34041" Txt="宝石を購入！" />
    <List Id="34042" Txt="ヒント：購入したい呪文をタップしてください。" />
    <List Id="34043" Txt="犠牲" />
    <List Id="34044" Txt="ノーマル" />
    <List Id="34045" Txt="エリート" />
    <List Id="34046" Txt="レジェンド" />
    <List Id="34047" Txt="宝石を獲得" />
    <List Id="34048" Txt="実行" />
    <List Id="34049" Txt="獲得" />
    <List Id="34050" Txt="無料の宝石！" />
    <List Id="34051" Txt="230宝石を購入してヒーローを獲得！" />
    <List Id="34052" Txt="600宝石を購入してヒーローを獲得！" />
    <List Id="34053" Txt="3,000宝石を購入してヒーローを獲得！" />
    <List Id="34054" Txt="15,000宝石を購入してヒーローを獲得！" />
    <List Id="34055" Txt="50,000宝石を購入してヒーローを獲得！" />
    <List Id="34056" Txt="交換" />
    <List Id="34057" Txt="この交換を行いますか？" />
    <List Id="34058" Txt="ここでは攻撃できません！別のエリアを選択してください。" />
    <List Id="34059" Txt="さらなるイベント！" />
    <List Id="34060" Txt="ターゲットにかけたい呪文をタップしてください！" />
    <List Id="34061" Txt="デバイスを傾けることで呪文をどこにかけるかコントロールできます！" />
    <List Id="34062" Txt="フェニックスの飛行を誘導できます！" />
    <List Id="34063" Txt="お支払いについて" />
    <List Id="34064" Txt="接続について" />
    <List Id="34065" Txt="その他について" />
    <List Id="34066" Txt="ご意見" />
    <List Id="34067" Txt="チャンス数：" />
    <List Id="34068" Txt="ヒーローの欠片がダンジョンに落ちているかも！" />
    <List Id="34069" Txt="ヒーローの配置" />
    <List Id="34070" Txt="魔法の購入" />
    <List Id="34071" Txt="レベル：" />
    <List Id="34072" Txt="ヒント：" />
    <List Id="34073" Txt="IGG ID：" />
    <List Id="34074" Txt="フォーラム" />
    <List Id="34075" Txt="音楽" />
    <List Id="34076" Txt="オン" />
    <List Id="34077" Txt="音響" />
    <List Id="34078" Txt="言語" />
    <List Id="34079" Txt="英語" />
    <List Id="34080" Txt="サービス利用規約" />
    <List Id="34081" Txt="バグの報告" />
    <List Id="34082" Txt="個人情報保護方針" />
    <List Id="34083" Txt="ライブサポート" />
    <List Id="34084" Txt="E メール" />
    <List Id="34085" Txt="バージョン 1.00" />
    <List Id="34086" Txt="Copyright 2012-2013 IGG.COM All Rights Reserved" />
    <List Id="34087" Txt="Help.castle.jp@igg.com" />
    <List Id="34088" Txt="OFF" />
    <List Id="34089" Txt="ヒーロー雇用" />
    <List Id="34090" Txt="栄光ポイント" />
    <List Id="34091" Txt="宝石" />
    <List Id="34092" Txt="欠片" />
    <List Id="34093" Txt="お知らせ" />
    <List Id="34094" Txt="友たちに教えて！" />
    <List Id="34095" Txt="アカウントはバインドしていません" />
    <List Id="34096" Txt="バインド" />
    <List Id="34097" Txt="このアカウントをバインドしてよろしいですか？" />
    <List Id="34098" Txt="切替" />
    <List Id="34099" Txt="アカウントを切替えてよろしいですか？" />
    <List Id="34100" Txt="バインドしました" />
    <List Id="34101" Txt="アカウントのバインドが成功した！" />
    <List Id="34102" Txt="アカウントのバインドが失敗した！" />
    <List Id="34103" Txt="メンテナンスの通知" />
    <List Id="34104" Txt="防御成功" />
    <List Id="34105" Txt="防御失敗" />
    <List Id="34106" Txt="友人" />
    <List Id="34107" Txt="PM" />
    <List Id="34108" Txt="友人を追加する" />
    <List Id="34109" Txt="アカウントの切替が失敗した" />
    <List Id="34110" Txt="ゲストでログイン" />
    <List Id="34111" Txt="アカウントがバインド中" />
    <List Id="34112" Txt="%sへ" />
    <List Id="34113" Txt="Google+アカウントにバインド" />
    <List Id="34114" Txt="アカウントが切替中" />
    <List Id="34115" Txt="アカウントの切替が成功した" />
    <List Id="34116" Txt="ご承認してから再びクリックして、アカウントのバインドを続けてください。" />
    <List Id="34117" Txt="友人を削除" />
    <List Id="34118" Txt="追加失敗、相手は既に友人です" />
    <List Id="34119" Txt="追加失敗、友人数は上限に達しています。" />
    <List Id="34120" Txt="攻撃間隔:" />
    <List Id="34121" Txt="このアカウントは既にバインドされています" />
    <List Id="34122" Txt="アップグレード条件" />
    <List Id="34123" Txt="ヒーロー防御能力：" />
    <List Id="34124" Txt="Translation is missing" />
    <List Id="34125" Txt="アカウントまだバンドしていないので、発言できません。アカウントバンドへ？" />
    <List Id="34126" Txt="Translation is missing" />
    <List Id="34127" Txt="Translation is missing" />
    <List Id="34128" Txt="完了" />
    <List Id="34129" Txt="Translation is missing" />
    <List Id="34130" Txt="ヒーロー防衛" />
    <List Id="34131" Txt="効果はヒーローのグレードによって違います。" />
    <List Id="34132" Txt="映像無効！" />
    <List Id="34133" Txt="該当するGmailは他のアカウントとバンドしました。" />
    <List Id="34134" Txt="Help.castle.apple@igg.com" />
    <List Id="34135" Txt="毎日00：00にランキングを更新する。" />
    <List Id="34136" Txt="Translation is missing" />
    <List Id="34137" Txt="Translation is missing" />
    <List Id="34138" Txt="ログアウトしてもう一度試してください。" />
    <List Id="34139" Txt="1-2時間以内もう一度試してください。" />
    <List Id="34140" Txt="このゲストアカウントが他のアカウントにバンドしました。
Gアカウントを変更して、もう一度試してください。" />
    <List Id="34141" Txt="このアカウントもうバンドしました。再びバンドする必要がありません。" />
    <List Id="34142" Txt="ランキングが更新しました。再び相手を選択してチャレンジください。" />
    <List Id="34143" Txt="91VIP特权礼包" />
    <List Id="34144" Txt="天盟&amp;91携手礼包" />
    <List Id="34145" Txt="現在の効果" />
    <List Id="34146" Txt="なし" />
    <List Id="34147" Txt="次のレベル" />
    <List Id="34148" Txt="最高のレベルに達しました" />
    <List Id="34149" Txt="招待" />
    <List Id="34150" Txt="友達招待！" />
    <List Id="34151" Txt="入って見よう！究極キャッスル攻防戦 - Castle Clash で遊んでるよ。早く入って、虐げて見よう！https://play.google.com/store/apps/details?id=com.igg.castleclash_jp" />
    <List Id="34152" Txt="公测大礼包" />
    <List Id="34153" Txt="争霸大礼包" />
    <List Id="34154" Txt="日本語" />
    <List Id="34155" Txt="关注小米游戏中心" />
    <List Id="34156" Txt="关注小米论坛" />
    <List Id="34157" Txt="才能チェンジ" />
    <List Id="34158" Txt="更新
" />
    <List Id="34159" Txt="新人ガイドをスキップしますか。" />
  </Text>
  <Text Type="14" TypeTxt="新炮臺信息">
    <List Id="35000" Txt="Translation is missing" />
    <List Id="35001" Txt="射程+3、ヒーローに優先攻撃する。" />
    <List Id="35002" Txt="射程を6点増加して、ヒーローに優先攻撃する。" />
    <List Id="35003" Txt="射程を9点増加して、ヒーローに優先攻撃する。" />
    <List Id="35004" Txt="射程を12点増加して、ヒーローに優先攻撃する。" />
    <List Id="35005" Txt="射程を15点増加して、ヒーローに優先攻撃する。" />
    <List Id="35011" Txt="ヒーローに150％ダメージを与える。" />
    <List Id="35012" Txt="ヒーローに200％傷を付ける。" />
    <List Id="35013" Txt="ヒーローに250％傷を付ける。" />
    <List Id="35014" Txt="ヒーローに300％傷を付ける。" />
    <List Id="35015" Txt="ヒーローに350％傷を付ける。" />
    <List Id="35021" Txt="自分のHP＋10％、ターゲットに与えるダメージが＋2％" />
    <List Id="35022" Txt="自分のHPを20％プラスして目標に傷4％プラスをつけさせる。" />
    <List Id="35023" Txt="自分のHPを30％プラスして目標に傷6％プラスをつけさせる。" />
    <List Id="35024" Txt="自分のHPを40％プラスして目標に傷8％プラスをつけさせる。" />
    <List Id="35025" Txt="自分のHPを50％プラスして目標に傷10％プラスをつけさせる。" />
    <List Id="35031" Txt="20％ダメージを増加する。" />
    <List Id="35032" Txt="傷を40％プラス。" />
    <List Id="35033" Txt="傷を60％プラス。" />
    <List Id="35034" Txt="傷を80％プラス。" />
    <List Id="35035" Txt="傷を100％プラス。" />
    <List Id="35041" Txt="砲弾射撃範囲＋1" />
    <List Id="35042" Txt="砲弾射撃範囲を2プラスさせる。" />
    <List Id="35043" Txt="砲弾射撃範囲を3プラスさせる。" />
    <List Id="35044" Txt="砲弾射撃範囲を4プラスさせる。" />
    <List Id="35045" Txt="砲弾射撃範囲を5プラスさせる。" />
    <List Id="35051" Txt="二つ砲弾連続発射する確率は15％。" />
    <List Id="35052" Txt="二つ砲弾連続発射する確率は25％。" />
    <List Id="35053" Txt="二つ砲弾連続発射する確率は35％。" />
    <List Id="35054" Txt="二つ砲弾連続発射する確率は45％。" />
    <List Id="35055" Txt="二つ砲弾連続発射する確率は55％。" />
    <List Id="35061" Txt="攻撃スピードは10％アップ。" />
    <List Id="35062" Txt="攻撃スピードは20％アップ。" />
    <List Id="35063" Txt="攻撃スピードは30％アップ。" />
    <List Id="35064" Txt="攻撃スピードは40％アップ。" />
    <List Id="35065" Txt="攻撃スピードは50％アップ。" />
    <List Id="35071" Txt="ターゲットを1.5秒昏睡させる確率が5％ある" />
    <List Id="35072" Txt="目標を1.5秒に倒すのは10％の確率があります。" />
    <List Id="35073" Txt="目標を1.5秒に倒すのは15％の確率があります。" />
    <List Id="35074" Txt="目標を1.5秒に倒すのは20％の確率があります。" />
    <List Id="35075" Txt="目標を1.5秒に倒すのは25％の確率があります。" />
    <List Id="35081" Txt="攻撃ターゲット+1，ダメージ+5%" />
    <List Id="35082" Txt="攻撃目標数を2プラスと、10％の傷を増加します。" />
    <List Id="35083" Txt="攻撃目標数を3プラスと、15％の傷を増加します。" />
    <List Id="35084" Txt="攻撃目標数を4プラスと、20％の傷を増加します。" />
    <List Id="35085" Txt="攻撃目標数を5プラスと、25％の傷を増加します。" />
  </Text>
  <Text Type="15" TypeTxt="公会信息">
    <List Id="36000" Txt="miss……" />
    <List Id="36001" Txt="miss……" />
    <List Id="36002" Txt="miss……" />
    <List Id="36003" Txt="miss……" />
    <List Id="36004" Txt="miss……" />
    <List Id="36005" Txt="miss……" />
    <List Id="36006" Txt="miss……" />
    <List Id="36007" Txt="miss……" />
    <List Id="36008" Txt="miss……" />
    <List Id="36009" Txt="miss……" />
    <List Id="36010" Txt="miss……" />
    <List Id="36011" Txt="miss……" />
    <List Id="36012" Txt="miss……" />
    <List Id="36013" Txt="miss……" />
    <List Id="36014" Txt="miss……" />
    <List Id="36015" Txt="miss……" />
    <List Id="36016" Txt="miss……" />
    <List Id="36017" Txt="miss……" />
    <List Id="36018" Txt="miss……" />
    <List Id="36019" Txt="miss……" />
    <List Id="36020" Txt="miss……" />
    <List Id="36021" Txt="miss……" />
    <List Id="36022" Txt="miss……" />
    <List Id="36023" Txt="miss……" />
    <List Id="36024" Txt="miss……" />
    <List Id="36025" Txt="miss……" />
    <List Id="36026" Txt="miss……" />
    <List Id="36027" Txt="miss……" />
    <List Id="36028" Txt="miss……" />
    <List Id="36029" Txt="miss……" />
    <List Id="36030" Txt="miss……" />
    <List Id="36031" Txt="miss……" />
    <List Id="36032" Txt="miss……" />
    <List Id="36033" Txt="miss……" />
    <List Id="36034" Txt="miss……" />
    <List Id="36035" Txt="miss……" />
    <List Id="36036" Txt="miss……" />
    <List Id="36037" Txt="miss……" />
    <List Id="36038" Txt="miss……" />
    <List Id="36039" Txt="miss……" />
    <List Id="36040" Txt="miss……" />
    <List Id="36041" Txt="miss……" />
    <List Id="36042" Txt="miss……" />
    <List Id="36043" Txt="miss……" />
    <List Id="36044" Txt="miss……" />
    <List Id="36045" Txt="miss……" />
    <List Id="36046" Txt="miss……" />
    <List Id="36047" Txt="miss……" />
    <List Id="36048" Txt="miss……" />
    <List Id="36049" Txt="miss……" />
    <List Id="36050" Txt="miss……" />
    <List Id="36051" Txt="miss……" />
    <List Id="36052" Txt="miss……" />
    <List Id="36053" Txt="miss……" />
    <List Id="36054" Txt="miss……" />
    <List Id="36055" Txt="miss……" />
    <List Id="36056" Txt="miss……" />
    <List Id="36057" Txt="miss……" />
    <List Id="36058" Txt="miss……" />
    <List Id="36059" Txt="miss……" />
    <List Id="36060" Txt="miss……" />
    <List Id="36061" Txt="miss……" />
    <List Id="36062" Txt="miss……" />
    <List Id="36063" Txt="miss……" />
    <List Id="36064" Txt="miss……" />
    <List Id="36065" Txt="miss……" />
    <List Id="36066" Txt="miss……" />
    <List Id="36067" Txt="miss……" />
    <List Id="36068" Txt="miss……" />
    <List Id="36069" Txt="miss……" />
    <List Id="36070" Txt="miss……" />
    <List Id="36071" Txt="miss……" />
    <List Id="36072" Txt="miss……" />
    <List Id="36073" Txt="miss……" />
    <List Id="36074" Txt="miss……" />
    <List Id="36075" Txt="miss……" />
    <List Id="36076" Txt="miss……" />
    <List Id="36077" Txt="miss……" />
    <List Id="36078" Txt="miss……" />
    <List Id="36079" Txt="miss……" />
    <List Id="36080" Txt="miss……" />
    <List Id="36081" Txt="miss……" />
    <List Id="36082" Txt="miss……" />
    <List Id="36083" Txt="miss……" />
    <List Id="36084" Txt="miss……" />
    <List Id="36085" Txt="miss……" />
    <List Id="36086" Txt="miss……" />
    <List Id="36087" Txt="miss……" />
    <List Id="36088" Txt="miss……" />
    <List Id="36089" Txt="miss……" />
    <List Id="36090" Txt="miss……" />
    <List Id="36091" Txt="miss……" />
    <List Id="36092" Txt="miss……" />
    <List Id="36093" Txt="miss……" />
    <List Id="36094" Txt="miss……" />
    <List Id="36095" Txt="miss……" />
    <List Id="36096" Txt="miss……" />
    <List Id="36097" Txt="miss……" />
    <List Id="36098" Txt="miss……" />
    <List Id="36099" Txt="miss……" />
    <List Id="36100" Txt="miss……" />
    <List Id="36101" Txt="miss……" />
    <List Id="36102" Txt="miss……" />
    <List />
    <List />
    <List />
    <List />
    <List />
    <List />
    <List />
    <List />
    <List />
    <List />
    <List />
    <List />
    <List />
    <List />
    <List />
    <List />
    <List />
    <List />
    <List />
    <List />
    <List />
    <List />
    <List />
    <List />
    <List />
    <List />
    <List />
    <List />
    <List />
    <List />
    <List />
    <List />
    <List />
    <List />
    <List />
    <List />
    <List />
    <List />
    <List />
    <List />
    <List />
    <List />
    <List />
    <List />
    <List />
    <List />
    <List />
    <List />
    <List />
    <List />
    <List />
    <List />
    <List />
    <List />
    <List />
    <List />
    <List />
    <List />
    <List />
    <List />
    <List />
  </Text>
</Config>

<!--
建表时间【2013.08.22】 by CXG
关联配置表：
Building.xml
-->
